Verilog Projects/T_Road_Trrafic_Signal_Controller/design.v
module hybrid_traffic_signal_control_fsm (
    input clk,
    input reset,
    input emergency_right,  // Emergency Right Mode (Stops both T1 and T2 for 10 mins)
    input emergency_left,   // Emergency Left Mode (Stops only T1)
    output reg [2:0] T1,         // T1 traffic light signal
    output reg [2:0] T2,         // T2 traffic light signal
    output reg buzzer_1,         // Buzzer for T1 (last 5s of RED)
    output reg buzzer_2,         // Buzzer for T2 (last 5s of RED)
    output reg T1_walk,          // Walk signal for T1
    output reg T2_walk           // Walk signal for T2
);

    // Traffic light states
    parameter RED = 2'b00, GREEN = 2'b01, YELLOW = 2'b10;
    reg [1:0] state_T1, next_state_T1;
    reg [1:0] state_T2, next_state_T2;

    reg [7:0] timer_T1;
    reg [7:0] timer_T2;
    reg [23:0] emergency_timer;

    // Time parameters
    parameter T_RED = 35;    // 35 sec @ 0.5s
    parameter T_GREEN = 30;  // 30 sec
    parameter T_YELLOW = 5; // 5 sec
    parameter EMERGENCY_TIME = 600; // 10 minutes (in clock cycles)

    // T1 FSM
    always @(posedge clk or posedge reset) begin
        if (reset) begin
            state_T1 <= RED;
            timer_T1 <= 0;
        end else if (emergency_right || emergency_left) begin
            state_T1 <= RED;
            timer_T1 <= 0;
        end else begin
            state_T1 <= next_state_T1;
            timer_T1 <= (state_T1 != next_state_T1) ? 0 : timer_T1 + 1;
        end
    end

    // T2 FSM
    always @(posedge clk or posedge reset) begin
        if (reset) begin
            state_T2 <= GREEN;
            timer_T2 <= 0;
            emergency_timer <= 0;
        end else if (emergency_right) begin
            if (emergency_timer < EMERGENCY_TIME) begin
                emergency_timer <= emergency_timer + 1;
                state_T2 <= RED;
            end else begin
                emergency_timer <= 0;
                state_T2 <= next_state_T2;
            end
        end else begin
            state_T2 <= next_state_T2;
            timer_T2 <= (state_T2 != next_state_T2) ? 0 : timer_T2 + 1;
        end
    end

    // T1 transition logic
    always @(*) begin
        next_state_T1 = state_T1;
        case (state_T1)
            RED:    if (timer_T1 >= T_RED)    next_state_T1 = GREEN;
            GREEN:  if (timer_T1 >= T_GREEN)  next_state_T1 = YELLOW;
            YELLOW: if (timer_T1 >= T_YELLOW) next_state_T1 = RED;
        endcase
    end

    // T2 transition logic
    always @(*) begin
        next_state_T2 = state_T2;
        case (state_T2)
            RED:    if (timer_T2 >= T_RED)    next_state_T2 = GREEN;
            GREEN:  if (timer_T2 >= T_GREEN)  next_state_T2 = YELLOW;
            YELLOW: if (timer_T2 >= T_YELLOW) next_state_T2 = RED;
        endcase
    end

    // Output logic
    always @(*) begin
        T1 = 3'b100;  // Default RED
        T2 = 3'b100;
        buzzer_1 = 0;
        buzzer_2 = 0;

        case (state_T1)
            RED: begin
                T1 = 3'b100;
                if (timer_T1 >= T_RED - 5) buzzer_1 = 1;  // last 5 sec
            end
            GREEN:  T1 = 3'b001;
            YELLOW: T1 = 3'b010;
        endcase

        case (state_T2)
            RED: begin
                T2 = 3'b100;
                if (timer_T2 >= T_RED - 5) buzzer_2 = 1;  // last 5 sec
            end
            GREEN:  T2 = 3'b001;
            YELLOW: T2 = 3'b010;
        endcase
    end

    // Walk signal logic
    always @(*) begin
        if (emergency_right || emergency_left) begin
            T1_walk = 0;
            T2_walk = 0;
        end else begin
            T1_walk = (state_T1 == RED || state_T1 == YELLOW) ? 1 : 0;
            T2_walk = (state_T2 == RED || state_T2 == YELLOW) ? 1 : 0;
        end
    end

endmodule

Verilog Projects/T_Road_Trrafic_Signal_Controller/testbench.v
`timescale 1s / 1ms  // 1 simulation second = 1 real millisecond

module tb_hybrid_traffic;

  reg clk, reset;
  reg emergency_right, emergency_left;
  wire [2:0] T1, T2;
  wire buzzer_1, buzzer_2;
  wire T1_walk, T2_walk;

  hybrid_traffic_signal_control_fsm uut (
    .clk(clk), .reset(reset),
    .emergency_right(emergency_right),
    .emergency_left(emergency_left),
    .T1(T1), .T2(T2),
    .buzzer_1(buzzer_1), .buzzer_2(buzzer_2),
    .T1_walk(T1_walk), .T2_walk(T2_walk)
  );

  // Clock generator: 1 Hz (1s period)
  initial clk = 0;
  always #0.5 clk = ~clk;

  initial begin
    $dumpfile("wave.vcd");
    $dumpvars(0, tb_hybrid_traffic);

    reset = 1; emergency_right = 0; emergency_left = 0;
    #2 reset = 0;

    // Run normal for a while
    #150;

    // Trigger emergency left (T1 stops)
    emergency_left = 1;
    #30 emergency_left = 0;

    // Trigger emergency right (T1 and T2 stop for 10 mins = 600s)
    emergency_right = 1;
    #20 emergency_right = 0;

    #1000 $finish;
  end

endmodule

Verilog Projects/T_Road_Trrafic_Signal_Controller/wave.vcd
$date
	Thu May  8 10:28:32 2025
$end
$version
	Icarus Verilog
$end
$timescale
	1ms
$end
$scope module tb_hybrid_traffic $end
$var wire 1 ! buzzer_2 $end
$var wire 1 " buzzer_1 $end
$var wire 1 # T2_walk $end
$var wire 3 $ T2 [2:0] $end
$var wire 1 % T1_walk $end
$var wire 3 & T1 [2:0] $end
$var reg 1 ' clk $end
$var reg 1 ( emergency_left $end
$var reg 1 ) emergency_right $end
$var reg 1 * reset $end
$scope module uut $end
$var wire 1 ' clk $end
$var wire 1 ( emergency_left $end
$var wire 1 ) emergency_right $end
$var wire 1 * reset $end
$var parameter 32 + EMERGENCY_TIME $end
$var parameter 2 , GREEN $end
$var parameter 2 - RED $end
$var parameter 32 . T_GREEN $end
$var parameter 32 / T_RED $end
$var parameter 32 0 T_YELLOW $end
$var parameter 2 1 YELLOW $end
$var reg 3 2 T1 [2:0] $end
$var reg 1 % T1_walk $end
$var reg 3 3 T2 [2:0] $end
$var reg 1 # T2_walk $end
$var reg 1 " buzzer_1 $end
$var reg 1 ! buzzer_2 $end
$var reg 24 4 emergency_timer [23:0] $end
$var reg 2 5 next_state_T1 [1:0] $end
$var reg 2 6 next_state_T2 [1:0] $end
$var reg 2 7 state_T1 [1:0] $end
$var reg 2 8 state_T2 [1:0] $end
$var reg 8 9 timer_T1 [7:0] $end
$var reg 8 : timer_T2 [7:0] $end
$upscope $end
$upscope $end
$enddefinitions $end
$comment Show the parameter values. $end
$dumpall
b10 1
b101 0
b100011 /
b11110 .
b0 -
b1 ,
b1001011000 +
$end
#0
$dumpvars
b0 :
b0 9
b1 8
b0 7
b1 6
b0 5
b0 4
b1 3
b100 2
1*
0)
0(
0'
b100 &
1%
b1 $
0#
0"
0!
$end
#500
1'
#1000
0'
#1500
1'
#2000
0'
0*
#2500
b1 $
b1 3
b1 :
b1 9
1'
#3000
0'
#3500
b1 $
b1 3
b10 9
b10 :
1'
#4000
0'
#4500
b1 $
b1 3
b11 :
b11 9
1'
#5000
0'
#5500
b1 $
b1 3
b100 9
b100 :
1'
#6000
0'
#6500
b1 $
b1 3
b101 :
b101 9
1'
#7000
0'
#7500
b1 $
b1 3
b110 9
b110 :
1'
#8000
0'
#8500
b1 $
b1 3
b111 :
b111 9
1'
#9000
0'
#9500
b1 $
b1 3
b1000 9
b1000 :
1'
#10000
0'
#10500
b1 $
b1 3
b1001 :
b1001 9
1'
#11000
0'
#11500
b1 $
b1 3
b1010 9
b1010 :
1'
#12000
0'
#12500
b1 $
b1 3
b1011 :
b1011 9
1'
#13000
0'
#13500
b1 $
b1 3
b1100 9
b1100 :
1'
#14000
0'
#14500
b1 $
b1 3
b1101 :
b1101 9
1'
#15000
0'
#15500
b1 $
b1 3
b1110 9
b1110 :
1'
#16000
0'
#16500
b1 $
b1 3
b1111 :
b1111 9
1'
#17000
0'
#17500
b1 $
b1 3
b10000 9
b10000 :
1'
#18000
0'
#18500
b1 $
b1 3
b10001 :
b10001 9
1'
#19000
0'
#19500
b1 $
b1 3
b10010 9
b10010 :
1'
#20000
0'
#20500
b1 $
b1 3
b10011 :
b10011 9
1'
#21000
0'
#21500
b1 $
b1 3
b10100 9
b10100 :
1'
#22000
0'
#22500
b1 $
b1 3
b10101 :
b10101 9
1'
#23000
0'
#23500
b1 $
b1 3
b10110 9
b10110 :
1'
#24000
0'
#24500
b1 $
b1 3
b10111 :
b10111 9
1'
#25000
0'
#25500
b1 $
b1 3
b11000 9
b11000 :
1'
#26000
0'
#26500
b1 $
b1 3
b11001 :
b11001 9
1'
#27000
0'
#27500
b1 $
b1 3
b11010 9
b11010 :
1'
#28000
0'
#28500
b1 $
b1 3
b11011 :
b11011 9
1'
#29000
0'
#29500
b1 $
b1 3
b11100 9
b11100 :
1'
#30000
0'
#30500
b1 $
b1 3
b11101 :
b11101 9
1'
#31000
0'
#31500
1"
b1 $
b1 3
b10 6
b11110 9
b11110 :
1'
#32000
0'
#32500
1#
1"
b10 $
b10 3
b0 :
b10 8
b11111 9
1'
#33000
0'
#33500
1"
b10 $
b10 3
b100000 9
b1 :
1'
#34000
0'
#34500
1"
b10 $
b10 3
b10 :
b100001 9
1'
#35000
0'
#35500
1"
b10 $
b10 3
b100010 9
b11 :
1'
#36000
0'
#36500
1"
b10 $
b10 3
b1 5
b100 :
b100011 9
1'
#37000
0'
#37500
0%
b1 &
b1 2
0"
b10 $
b10 3
b0 6
b0 9
b1 7
b101 :
1'
#38000
0'
#38500
b100 $
b100 3
b1 &
b1 2
b0 :
b0 8
b1 9
1'
#39000
0'
#39500
b1 &
b1 2
b10 9
b1 :
1'
#40000
0'
#40500
b1 &
b1 2
b10 :
b11 9
1'
#41000
0'
#41500
b1 &
b1 2
b100 9
b11 :
1'
#42000
0'
#42500
b1 &
b1 2
b100 :
b101 9
1'
#43000
0'
#43500
b1 &
b1 2
b110 9
b101 :
1'
#44000
0'
#44500
b1 &
b1 2
b110 :
b111 9
1'
#45000
0'
#45500
b1 &
b1 2
b1000 9
b111 :
1'
#46000
0'
#46500
b1 &
b1 2
b1000 :
b1001 9
1'
#47000
0'
#47500
b1 &
b1 2
b1010 9
b1001 :
1'
#48000
0'
#48500
b1 &
b1 2
b1010 :
b1011 9
1'
#49000
0'
#49500
b1 &
b1 2
b1100 9
b1011 :
1'
#50000
0'
#50500
b1 &
b1 2
b1100 :
b1101 9
1'
#51000
0'
#51500
b1 &
b1 2
b1110 9
b1101 :
1'
#52000
0'
#52500
b1 &
b1 2
b1110 :
b1111 9
1'
#53000
0'
#53500
b1 &
b1 2
b10000 9
b1111 :
1'
#54000
0'
#54500
b1 &
b1 2
b10000 :
b10001 9
1'
#55000
0'
#55500
b1 &
b1 2
b10010 9
b10001 :
1'
#56000
0'
#56500
b1 &
b1 2
b10010 :
b10011 9
1'
#57000
0'
#57500
b1 &
b1 2
b10100 9
b10011 :
1'
#58000
0'
#58500
b1 &
b1 2
b10100 :
b10101 9
1'
#59000
0'
#59500
b1 &
b1 2
b10110 9
b10101 :
1'
#60000
0'
#60500
b1 &
b1 2
b10110 :
b10111 9
1'
#61000
0'
#61500
b1 &
b1 2
b11000 9
b10111 :
1'
#62000
0'
#62500
b1 &
b1 2
b11000 :
b11001 9
1'
#63000
0'
#63500
b1 &
b1 2
b11010 9
b11001 :
1'
#64000
0'
#64500
b1 &
b1 2
b11010 :
b11011 9
1'
#65000
0'
#65500
b1 &
b1 2
b11100 9
b11011 :
1'
#66000
0'
#66500
b1 &
b1 2
b11100 :
b11101 9
1'
#67000
0'
#67500
b10 5
b1 &
b1 2
b11110 9
b11101 :
1'
#68000
0'
#68500
1%
1!
b10 &
b10 2
b11110 :
b0 9
b10 7
1'
#69000
0'
#69500
1!
b10 &
b10 2
b1 9
b11111 :
1'
#70000
0'
#70500
1!
b10 &
b10 2
b100000 :
b10 9
1'
#71000
0'
#71500
1!
b10 &
b10 2
b11 9
b100001 :
1'
#72000
0'
#72500
1!
b10 &
b10 2
b100010 :
b100 9
1'
#73000
0'
#73500
b0 5
1!
b10 &
b10 2
b1 6
b101 9
b100011 :
1'
#74000
0'
#74500
0#
b1 $
b1 3
0!
b100 &
b100 2
b0 :
b1 8
b0 9
b0 7
1'
#75000
0'
#75500
b1 $
b1 3
b1 9
b1 :
1'
#76000
0'
#76500
b1 $
b1 3
b10 :
b10 9
1'
#77000
0'
#77500
b1 $
b1 3
b11 9
b11 :
1'
#78000
0'
#78500
b1 $
b1 3
b100 :
b100 9
1'
#79000
0'
#79500
b1 $
b1 3
b101 9
b101 :
1'
#80000
0'
#80500
b1 $
b1 3
b110 :
b110 9
1'
#81000
0'
#81500
b1 $
b1 3
b111 9
b111 :
1'
#82000
0'
#82500
b1 $
b1 3
b1000 :
b1000 9
1'
#83000
0'
#83500
b1 $
b1 3
b1001 9
b1001 :
1'
#84000
0'
#84500
b1 $
b1 3
b1010 :
b1010 9
1'
#85000
0'
#85500
b1 $
b1 3
b1011 9
b1011 :
1'
#86000
0'
#86500
b1 $
b1 3
b1100 :
b1100 9
1'
#87000
0'
#87500
b1 $
b1 3
b1101 9
b1101 :
1'
#88000
0'
#88500
b1 $
b1 3
b1110 :
b1110 9
1'
#89000
0'
#89500
b1 $
b1 3
b1111 9
b1111 :
1'
#90000
0'
#90500
b1 $
b1 3
b10000 :
b10000 9
1'
#91000
0'
#91500
b1 $
b1 3
b10001 9
b10001 :
1'
#92000
0'
#92500
b1 $
b1 3
b10010 :
b10010 9
1'
#93000
0'
#93500
b1 $
b1 3
b10011 9
b10011 :
1'
#94000
0'
#94500
b1 $
b1 3
b10100 :
b10100 9
1'
#95000
0'
#95500
b1 $
b1 3
b10101 9
b10101 :
1'
#96000
0'
#96500
b1 $
b1 3
b10110 :
b10110 9
1'
#97000
0'
#97500
b1 $
b1 3
b10111 9
b10111 :
1'
#98000
0'
#98500
b1 $
b1 3
b11000 :
b11000 9
1'
#99000
0'
#99500
b1 $
b1 3
b11001 9
b11001 :
1'
#100000
0'
#100500
b1 $
b1 3
b11010 :
b11010 9
1'
#101000
0'
#101500
b1 $
b1 3
b11011 9
b11011 :
1'
#102000
0'
#102500
b1 $
b1 3
b11100 :
b11100 9
1'
#103000
0'
#103500
b1 $
b1 3
b11101 9
b11101 :
1'
#104000
0'
#104500
b10 6
1"
b1 $
b1 3
b11110 :
b11110 9
1'
#105000
0'
#105500
1#
1"
b10 $
b10 3
b11111 9
b0 :
b10 8
1'
#106000
0'
#106500
1"
b10 $
b10 3
b1 :
b100000 9
1'
#107000
0'
#107500
1"
b10 $
b10 3
b100001 9
b10 :
1'
#108000
0'
#108500
1"
b10 $
b10 3
b11 :
b100010 9
1'
#109000
0'
#109500
b1 5
1"
b10 $
b10 3
b100011 9
b100 :
1'
#110000
0'
#110500
b0 6
0%
b1 &
b1 2
0"
b10 $
b10 3
b101 :
b0 9
b1 7
1'
#111000
0'
#111500
b100 $
b100 3
b1 &
b1 2
b1 9
b0 :
b0 8
1'
#112000
0'
#112500
b1 &
b1 2
b1 :
b10 9
1'
#113000
0'
#113500
b1 &
b1 2
b11 9
b10 :
1'
#114000
0'
#114500
b1 &
b1 2
b11 :
b100 9
1'
#115000
0'
#115500
b1 &
b1 2
b101 9
b100 :
1'
#116000
0'
#116500
b1 &
b1 2
b101 :
b110 9
1'
#117000
0'
#117500
b1 &
b1 2
b111 9
b110 :
1'
#118000
0'
#118500
b1 &
b1 2
b111 :
b1000 9
1'
#119000
0'
#119500
b1 &
b1 2
b1001 9
b1000 :
1'
#120000
0'
#120500
b1 &
b1 2
b1001 :
b1010 9
1'
#121000
0'
#121500
b1 &
b1 2
b1011 9
b1010 :
1'
#122000
0'
#122500
b1 &
b1 2
b1011 :
b1100 9
1'
#123000
0'
#123500
b1 &
b1 2
b1101 9
b1100 :
1'
#124000
0'
#124500
b1 &
b1 2
b1101 :
b1110 9
1'
#125000
0'
#125500
b1 &
b1 2
b1111 9
b1110 :
1'
#126000
0'
#126500
b1 &
b1 2
b1111 :
b10000 9
1'
#127000
0'
#127500
b1 &
b1 2
b10001 9
b10000 :
1'
#128000
0'
#128500
b1 &
b1 2
b10001 :
b10010 9
1'
#129000
0'
#129500
b1 &
b1 2
b10011 9
b10010 :
1'
#130000
0'
#130500
b1 &
b1 2
b10011 :
b10100 9
1'
#131000
0'
#131500
b1 &
b1 2
b10101 9
b10100 :
1'
#132000
0'
#132500
b1 &
b1 2
b10101 :
b10110 9
1'
#133000
0'
#133500
b1 &
b1 2
b10111 9
b10110 :
1'
#134000
0'
#134500
b1 &
b1 2
b10111 :
b11000 9
1'
#135000
0'
#135500
b1 &
b1 2
b11001 9
b11000 :
1'
#136000
0'
#136500
b1 &
b1 2
b11001 :
b11010 9
1'
#137000
0'
#137500
b1 &
b1 2
b11011 9
b11010 :
1'
#138000
0'
#138500
b1 &
b1 2
b11011 :
b11100 9
1'
#139000
0'
#139500
b1 &
b1 2
b11101 9
b11100 :
1'
#140000
0'
#140500
b1 &
b1 2
b10 5
b11101 :
b11110 9
1'
#141000
0'
#141500
1%
1!
b10 &
b10 2
b0 9
b10 7
b11110 :
1'
#142000
0'
#142500
1!
b10 &
b10 2
b11111 :
b1 9
1'
#143000
0'
#143500
1!
b10 &
b10 2
b10 9
b100000 :
1'
#144000
0'
#144500
1!
b10 &
b10 2
b100001 :
b11 9
1'
#145000
0'
#145500
1!
b10 &
b10 2
b100 9
b100010 :
1'
#146000
0'
#146500
b1 6
1!
b10 &
b10 2
b0 5
b100011 :
b101 9
1'
#147000
0'
#147500
0#
b1 $
b1 3
0!
b100 &
b100 2
b0 9
b0 7
b0 :
b1 8
1'
#148000
0'
#148500
b1 $
b1 3
b1 :
b1 9
1'
#149000
0'
#149500
b1 $
b1 3
b10 9
b10 :
1'
#150000
0'
#150500
b1 $
b1 3
b11 :
b11 9
1'
#151000
0'
#151500
b1 $
b1 3
b100 9
b100 :
1'
#152000
0%
0'
1(
#152500
b1 $
b1 3
b101 :
b0 9
1'
#153000
0'
#153500
b1 $
b1 3
b110 :
1'
#154000
0'
#154500
b1 $
b1 3
b111 :
1'
#155000
0'
#155500
b1 $
b1 3
b1000 :
1'
#156000
0'
#156500
b1 $
b1 3
b1001 :
1'
#157000
0'
#157500
b1 $
b1 3
b1010 :
1'
#158000
0'
#158500
b1 $
b1 3
b1011 :
1'
#159000
0'
#159500
b1 $
b1 3
b1100 :
1'
#160000
0'
#160500
b1 $
b1 3
b1101 :
1'
#161000
0'
#161500
b1 $
b1 3
b1110 :
1'
#162000
0'
#162500
b1 $
b1 3
b1111 :
1'
#163000
0'
#163500
b1 $
b1 3
b10000 :
1'
#164000
0'
#164500
b1 $
b1 3
b10001 :
1'
#165000
0'
#165500
b1 $
b1 3
b10010 :
1'
#166000
0'
#166500
b1 $
b1 3
b10011 :
1'
#167000
0'
#167500
b1 $
b1 3
b10100 :
1'
#168000
0'
#168500
b1 $
b1 3
b10101 :
1'
#169000
0'
#169500
b1 $
b1 3
b10110 :
1'
#170000
0'
#170500
b1 $
b1 3
b10111 :
1'
#171000
0'
#171500
b1 $
b1 3
b11000 :
1'
#172000
0'
#172500
b1 $
b1 3
b11001 :
1'
#173000
0'
#173500
b1 $
b1 3
b11010 :
1'
#174000
0'
#174500
b1 $
b1 3
b11011 :
1'
#175000
0'
#175500
b1 $
b1 3
b11100 :
1'
#176000
0'
#176500
b1 $
b1 3
b11101 :
1'
#177000
0'
#177500
b1 $
b1 3
b10 6
b11110 :
1'
#178000
0'
#178500
b10 $
b10 3
b0 :
b10 8
1'
#179000
0'
#179500
b10 $
b10 3
b1 :
1'
#180000
0'
#180500
b10 $
b10 3
b10 :
1'
#181000
0'
#181500
b10 $
b10 3
b11 :
1'
#182000
0'
1)
0(
#182500
b100 $
b100 3
b0 6
b0 8
b1 4
1'
#183000
0'
#183500
b10 4
1'
#184000
0'
#184500
b11 4
1'
#185000
0'
#185500
b100 4
1'
#186000
0'
#186500
b101 4
1'
#187000
0'
#187500
b110 4
1'
#188000
0'
#188500
b111 4
1'
#189000
0'
#189500
b1000 4
1'
#190000
0'
#190500
b1001 4
1'
#191000
0'
#191500
b1010 4
1'
#192000
0'
#192500
b1011 4
1'
#193000
0'
#193500
b1100 4
1'
#194000
0'
#194500
b1101 4
1'
#195000
0'
#195500
b1110 4
1'
#196000
0'
#196500
b1111 4
1'
#197000
0'
#197500
b10000 4
1'
#198000
0'
#198500
b10001 4
1'
#199000
0'
#199500
b10010 4
1'
#200000
0'
#200500
b10011 4
1'
#201000
0'
#201500
b10100 4
1'
#202000
1#
1%
0'
0)
#202500
b100 :
b1 9
1'
#203000
0'
#203500
b10 9
b101 :
1'
#204000
0'
#204500
b110 :
b11 9
1'
#205000
0'
#205500
b100 9
b111 :
1'
#206000
0'
#206500
b1000 :
b101 9
1'
#207000
0'
#207500
b110 9
b1001 :
1'
#208000
0'
#208500
b1010 :
b111 9
1'
#209000
0'
#209500
b1000 9
b1011 :
1'
#210000
0'
#210500
b1100 :
b1001 9
1'
#211000
0'
#211500
b1010 9
b1101 :
1'
#212000
0'
#212500
b1110 :
b1011 9
1'
#213000
0'
#213500
b1100 9
b1111 :
1'
#214000
0'
#214500
b10000 :
b1101 9
1'
#215000
0'
#215500
b1110 9
b10001 :
1'
#216000
0'
#216500
b10010 :
b1111 9
1'
#217000
0'
#217500
b10000 9
b10011 :
1'
#218000
0'
#218500
b10100 :
b10001 9
1'
#219000
0'
#219500
b10010 9
b10101 :
1'
#220000
0'
#220500
b10110 :
b10011 9
1'
#221000
0'
#221500
b10100 9
b10111 :
1'
#222000
0'
#222500
b11000 :
b10101 9
1'
#223000
0'
#223500
b10110 9
b11001 :
1'
#224000
0'
#224500
b11010 :
b10111 9
1'
#225000
0'
#225500
b11000 9
b11011 :
1'
#226000
0'
#226500
b11100 :
b11001 9
1'
#227000
0'
#227500
b11010 9
b11101 :
1'
#228000
0'
#228500
1!
b11110 :
b11011 9
1'
#229000
0'
#229500
1!
b11100 9
b11111 :
1'
#230000
0'
#230500
1!
b100000 :
b11101 9
1'
#231000
0'
#231500
1"
1!
b11110 9
b100001 :
1'
#232000
0'
#232500
1!
1"
b100010 :
b11111 9
1'
#233000
0'
#233500
1!
1"
b1 6
b100000 9
b100011 :
1'
#234000
0'
#234500
0#
b1 $
b1 3
0!
1"
b0 :
b1 8
b100001 9
1'
#235000
0'
#235500
1"
b1 $
b1 3
b100010 9
b1 :
1'
#236000
0'
#236500
1"
b1 $
b1 3
b1 5
b10 :
b100011 9
1'
#237000
0'
#237500
0%
b1 &
b1 2
0"
b1 $
b1 3
b0 9
b1 7
b11 :
1'
#238000
0'
#238500
b1 $
b1 3
b1 &
b1 2
b100 :
b1 9
1'
#239000
0'
#239500
b1 $
b1 3
b1 &
b1 2
b10 9
b101 :
1'
#240000
0'
#240500
b1 $
b1 3
b1 &
b1 2
b110 :
b11 9
1'
#241000
0'
#241500
b1 $
b1 3
b1 &
b1 2
b100 9
b111 :
1'
#242000
0'
#242500
b1 $
b1 3
b1 &
b1 2
b1000 :
b101 9
1'
#243000
0'
#243500
b1 $
b1 3
b1 &
b1 2
b110 9
b1001 :
1'
#244000
0'
#244500
b1 $
b1 3
b1 &
b1 2
b1010 :
b111 9
1'
#245000
0'
#245500
b1 $
b1 3
b1 &
b1 2
b1000 9
b1011 :
1'
#246000
0'
#246500
b1 $
b1 3
b1 &
b1 2
b1100 :
b1001 9
1'
#247000
0'
#247500
b1 $
b1 3
b1 &
b1 2
b1010 9
b1101 :
1'
#248000
0'
#248500
b1 $
b1 3
b1 &
b1 2
b1110 :
b1011 9
1'
#249000
0'
#249500
b1 $
b1 3
b1 &
b1 2
b1100 9
b1111 :
1'
#250000
0'
#250500
b1 $
b1 3
b1 &
b1 2
b10000 :
b1101 9
1'
#251000
0'
#251500
b1 $
b1 3
b1 &
b1 2
b1110 9
b10001 :
1'
#252000
0'
#252500
b1 $
b1 3
b1 &
b1 2
b10010 :
b1111 9
1'
#253000
0'
#253500
b1 $
b1 3
b1 &
b1 2
b10000 9
b10011 :
1'
#254000
0'
#254500
b1 $
b1 3
b1 &
b1 2
b10100 :
b10001 9
1'
#255000
0'
#255500
b1 $
b1 3
b1 &
b1 2
b10010 9
b10101 :
1'
#256000
0'
#256500
b1 $
b1 3
b1 &
b1 2
b10110 :
b10011 9
1'
#257000
0'
#257500
b1 $
b1 3
b1 &
b1 2
b10100 9
b10111 :
1'
#258000
0'
#258500
b1 $
b1 3
b1 &
b1 2
b11000 :
b10101 9
1'
#259000
0'
#259500
b1 $
b1 3
b1 &
b1 2
b10110 9
b11001 :
1'
#260000
0'
#260500
b1 $
b1 3
b1 &
b1 2
b11010 :
b10111 9
1'
#261000
0'
#261500
b1 $
b1 3
b1 &
b1 2
b11000 9
b11011 :
1'
#262000
0'
#262500
b1 $
b1 3
b1 &
b1 2
b11100 :
b11001 9
1'
#263000
0'
#263500
b1 $
b1 3
b1 &
b1 2
b11010 9
b11101 :
1'
#264000
0'
#264500
b10 6
b1 $
b1 3
b1 &
b1 2
b11110 :
b11011 9
1'
#265000
0'
#265500
1#
b10 $
b10 3
b1 &
b1 2
b11100 9
b0 :
b10 8
1'
#266000
0'
#266500
b10 $
b10 3
b1 &
b1 2
b1 :
b11101 9
1'
#267000
0'
#267500
b10 5
b10 $
b10 3
b1 &
b1 2
b11110 9
b10 :
1'
#268000
0'
#268500
1%
b10 $
b10 3
b10 &
b10 2
b11 :
b0 9
b10 7
1'
#269000
0'
#269500
b10 $
b10 3
b10 &
b10 2
b1 9
b100 :
1'
#270000
0'
#270500
b0 6
b10 $
b10 3
b10 &
b10 2
b101 :
b10 9
1'
#271000
0'
#271500
b100 $
b100 3
b10 &
b10 2
b11 9
b0 :
b0 8
1'
#272000
0'
#272500
b10 &
b10 2
b1 :
b100 9
1'
#273000
0'
#273500
b0 5
b10 &
b10 2
b101 9
b10 :
1'
#274000
0'
#274500
b100 &
b100 2
b11 :
b0 9
b0 7
1'
#275000
0'
#275500
b1 9
b100 :
1'
#276000
0'
#276500
b101 :
b10 9
1'
#277000
0'
#277500
b11 9
b110 :
1'
#278000
0'
#278500
b111 :
b100 9
1'
#279000
0'
#279500
b101 9
b1000 :
1'
#280000
0'
#280500
b1001 :
b110 9
1'
#281000
0'
#281500
b111 9
b1010 :
1'
#282000
0'
#282500
b1011 :
b1000 9
1'
#283000
0'
#283500
b1001 9
b1100 :
1'
#284000
0'
#284500
b1101 :
b1010 9
1'
#285000
0'
#285500
b1011 9
b1110 :
1'
#286000
0'
#286500
b1111 :
b1100 9
1'
#287000
0'
#287500
b1101 9
b10000 :
1'
#288000
0'
#288500
b10001 :
b1110 9
1'
#289000
0'
#289500
b1111 9
b10010 :
1'
#290000
0'
#290500
b10011 :
b10000 9
1'
#291000
0'
#291500
b10001 9
b10100 :
1'
#292000
0'
#292500
b10101 :
b10010 9
1'
#293000
0'
#293500
b10011 9
b10110 :
1'
#294000
0'
#294500
b10111 :
b10100 9
1'
#295000
0'
#295500
b10101 9
b11000 :
1'
#296000
0'
#296500
b11001 :
b10110 9
1'
#297000
0'
#297500
b10111 9
b11010 :
1'
#298000
0'
#298500
b11011 :
b11000 9
1'
#299000
0'
#299500
b11001 9
b11100 :
1'
#300000
0'
#300500
b11101 :
b11010 9
1'
#301000
0'
#301500
1!
b11011 9
b11110 :
1'
#302000
0'
#302500
1!
b11111 :
b11100 9
1'
#303000
0'
#303500
1!
b11101 9
b100000 :
1'
#304000
0'
#304500
1"
1!
b100001 :
b11110 9
1'
#305000
0'
#305500
1!
1"
b11111 9
b100010 :
1'
#306000
0'
#306500
b1 6
1!
1"
b100011 :
b100000 9
1'
#307000
0'
#307500
0#
b1 $
b1 3
0!
1"
b100001 9
b0 :
b1 8
1'
#308000
0'
#308500
1"
b1 $
b1 3
b1 :
b100010 9
1'
#309000
0'
#309500
b1 5
1"
b1 $
b1 3
b100011 9
b10 :
1'
#310000
0'
#310500
0%
b1 &
b1 2
0"
b1 $
b1 3
b11 :
b0 9
b1 7
1'
#311000
0'
#311500
b1 $
b1 3
b1 &
b1 2
b1 9
b100 :
1'
#312000
0'
#312500
b1 $
b1 3
b1 &
b1 2
b101 :
b10 9
1'
#313000
0'
#313500
b1 $
b1 3
b1 &
b1 2
b11 9
b110 :
1'
#314000
0'
#314500
b1 $
b1 3
b1 &
b1 2
b111 :
b100 9
1'
#315000
0'
#315500
b1 $
b1 3
b1 &
b1 2
b101 9
b1000 :
1'
#316000
0'
#316500
b1 $
b1 3
b1 &
b1 2
b1001 :
b110 9
1'
#317000
0'
#317500
b1 $
b1 3
b1 &
b1 2
b111 9
b1010 :
1'
#318000
0'
#318500
b1 $
b1 3
b1 &
b1 2
b1011 :
b1000 9
1'
#319000
0'
#319500
b1 $
b1 3
b1 &
b1 2
b1001 9
b1100 :
1'
#320000
0'
#320500
b1 $
b1 3
b1 &
b1 2
b1101 :
b1010 9
1'
#321000
0'
#321500
b1 $
b1 3
b1 &
b1 2
b1011 9
b1110 :
1'
#322000
0'
#322500
b1 $
b1 3
b1 &
b1 2
b1111 :
b1100 9
1'
#323000
0'
#323500
b1 $
b1 3
b1 &
b1 2
b1101 9
b10000 :
1'
#324000
0'
#324500
b1 $
b1 3
b1 &
b1 2
b10001 :
b1110 9
1'
#325000
0'
#325500
b1 $
b1 3
b1 &
b1 2
b1111 9
b10010 :
1'
#326000
0'
#326500
b1 $
b1 3
b1 &
b1 2
b10011 :
b10000 9
1'
#327000
0'
#327500
b1 $
b1 3
b1 &
b1 2
b10001 9
b10100 :
1'
#328000
0'
#328500
b1 $
b1 3
b1 &
b1 2
b10101 :
b10010 9
1'
#329000
0'
#329500
b1 $
b1 3
b1 &
b1 2
b10011 9
b10110 :
1'
#330000
0'
#330500
b1 $
b1 3
b1 &
b1 2
b10111 :
b10100 9
1'
#331000
0'
#331500
b1 $
b1 3
b1 &
b1 2
b10101 9
b11000 :
1'
#332000
0'
#332500
b1 $
b1 3
b1 &
b1 2
b11001 :
b10110 9
1'
#333000
0'
#333500
b1 $
b1 3
b1 &
b1 2
b10111 9
b11010 :
1'
#334000
0'
