Verilog Projects/Fixed_point_ADD,SUB,MUL/fixed_point_operations.v
`timescale 1ns/1ps

module fixed_point_operations (
    input  signed [16:0] q_314,        
    input  signed [16:0] q_512,        
    input  [1:0]         operation,
    input                clk,
    output reg signed [16:0] out_q_512 
);

    reg signed [16:0] q314_r;
    reg signed [16:0] q512_r;
    reg [1:0]         op_r;

    always @(posedge clk) begin
        q314_r <= q_314;
        q512_r <= q_512;
        op_r   <= operation;
    end

    
    wire signed [18:0] q314_ext;
    assign q314_ext = { {2{q314_r[16]}}, q314_r };

    wire signed [16:0] q314_to_q512;
    assign q314_to_q512 = (q314_ext + 19'sd2) >>> 2;

    
    wire signed [17:0] add_wide;
    wire signed [17:0] sub_wide;
    wire signed [33:0] mult_full;

    assign add_wide = q512_r + q314_to_q512;
    assign sub_wide = q512_r - q314_to_q512;
    assign mult_full = q314_r * q512_r;

    // Round before shifting
    wire signed [33:0] mult_rounded;
    assign mult_rounded = mult_full + (34'sd1 << 13);

    wire signed [16:0] mult_q512;
    assign mult_q512 = mult_rounded >>> 14;

    
    always @(posedge clk) begin
        case (op_r)
            2'b00: out_q_512 <= add_wide[16:0];          
            2'b01: out_q_512 <= sub_wide[17:1];          
            2'b10: out_q_512 <= mult_q512;               
            default: out_q_512 <= 17'sd0;
        endcase
    end

endmodule

Verilog Projects/Fixed_point_ADD,SUB,MUL/tb_fixed_point_operations.v
`timescale 1ns/1ps

module tb_fixed_point_operations;

    
    reg clk;
    localparam integer CLK_PERIOD = 20833; // ns

    initial begin
        clk = 1'b0;
        forever #(CLK_PERIOD/2) clk = ~clk;
    end

    
    reg  signed [16:0] q_314;
    reg  signed [16:0] q_512;
    reg  [1:0]         operation;
    wire signed [16:0] out_q_512;

    
    fixed_point_operations dut (
        .q_314     (q_314),
        .q_512     (q_512),
        .operation (operation),
        .clk       (clk),
        .out_q_512 (out_q_512)
    );

    
    reg signed [16:0] q314_mem [0:479];
    reg signed [16:0] q512_mem [0:479];

    integer infile;
    integer add_file, sub_file, mul_file;
    integer i, status;
    reg [1023:0] header;

    
    initial begin
        $dumpfile("tb_fixed_point_operations.vcd");
        $dumpvars(0, tb_fixed_point_operations);
    end

    
    initial begin
        infile = $fopen("sine_q314_q512_binary.csv", "r");
        if (infile == 0) begin
            $display("ERROR: Cannot open input CSV");
            $finish;
        end

        // Skip header
        $fgets(header, infile);

        // Read 480 samples
        for (i = 0; i < 480; i = i + 1) begin
            status = $fscanf(
                infile,
                "%*d,%b,%*d,%b\n",
                q314_mem[i],
                q512_mem[i]
            );

            if (status != 2) begin
                $display("ERROR: CSV read failed at sample %0d", i);
                $finish;
            end
        end
        $fclose(infile);

        
        add_file = $fopen("results_add.csv", "w");
        sub_file = $fopen("results_sub.csv", "w");
        mul_file = $fopen("results_mul.csv", "w");

        if (add_file == 0 || sub_file == 0 || mul_file == 0) begin
            $display("ERROR: Cannot open output CSVs");
            $finish;
        end

        $fwrite(add_file, "q314,q512,add_out\n");
        $fwrite(sub_file, "q314,q512,sub_out\n");
        $fwrite(mul_file, "q314,q512,mul_out\n");

        
        q_314     = 0;
        q_512     = 0;
        operation = 0;
        @(posedge clk);

        
        operation = 2'b00;

        // Prime pipeline
        q_314 = q314_mem[0];
        q_512 = q512_mem[0];
        @(posedge clk);

        for (i = 1; i < 480; i = i + 1) begin
            q_314 = q314_mem[i];
            q_512 = q512_mem[i];
            @(posedge clk);

            $fwrite(add_file, "%0d,%0d,%0d\n",
                    q314_mem[i-1],
                    q512_mem[i-1],
                    out_q_512);
        end

        
        operation = 2'b01;

        q_314 = q314_mem[0];
        q_512 = q512_mem[0];
        @(posedge clk);

        for (i = 1; i < 480; i = i + 1) begin
            q_314 = q314_mem[i];
            q_512 = q512_mem[i];
            @(posedge clk);

            $fwrite(sub_file, "%0d,%0d,%0d\n",
                    q314_mem[i-1],
                    q512_mem[i-1],
                    out_q_512);
        end

        
        operation = 2'b10;

        q_314 = q314_mem[0];
        q_512 = q512_mem[0];
        @(posedge clk);

        for (i = 1; i < 480; i = i + 1) begin
            q_314 = q314_mem[i];
            q_512 = q512_mem[i];
            @(posedge clk);

            $fwrite(mul_file, "%0d,%0d,%0d\n",
                    q314_mem[i-1],
                    q512_mem[i-1],
                    out_q_512);
        end

        
        $fclose(add_file);
        $fclose(sub_file);
        $fclose(mul_file);

        $display("Simulation completed successfully");
        $finish;
    end

endmodule

Verilog Projects/Fixed_point_ADD,SUB,MUL/tb_fixed_point_operations.vcd
$date
	Wed Feb 04 15:39:26 2026
$end
$version
	Icarus Verilog
$end
$timescale
	1ps
$end
$scope module tb_fixed_point_operations $end
$var wire 17 ! out_q_512 [16:0] $end
$var parameter 32 " CLK_PERIOD $end
$var reg 1 # clk $end
$var reg 1024 $ header [1023:0] $end
$var reg 2 % operation [1:0] $end
$var reg 17 & q_314 [16:0] $end
$var reg 17 ' q_512 [16:0] $end
$var integer 32 ( add_file [31:0] $end
$var integer 32 ) i [31:0] $end
$var integer 32 * infile [31:0] $end
$var integer 32 + mul_file [31:0] $end
$var integer 32 , status [31:0] $end
$var integer 32 - sub_file [31:0] $end
$scope module dut $end
$var wire 1 # clk $end
$var wire 2 . operation [1:0] $end
$var wire 17 / q_314 [16:0] $end
$var wire 17 0 q_512 [16:0] $end
$var wire 18 1 sub_wide [17:0] $end
$var wire 17 2 q314_to_q512 [16:0] $end
$var wire 19 3 q314_ext [18:0] $end
$var wire 34 4 mult_rounded [33:0] $end
$var wire 17 5 mult_q512 [16:0] $end
$var wire 34 6 mult_full [33:0] $end
$var wire 18 7 add_wide [17:0] $end
$var reg 2 8 op_r [1:0] $end
$var reg 17 9 out_q_512 [16:0] $end
$var reg 17 : q314_r [16:0] $end
$var reg 17 ; q512_r [16:0] $end
$upscope $end
$upscope $end
$enddefinitions $end
$comment Show the parameter values. $end
$dumpall
b101000101100001 "
$end
#0
$dumpvars
bx ;
bx :
bx 9
bx 8
bx 7
bx 6
bx 5
bx 4
bx 3
bx 2
bx 1
b0 0
b0 /
b0 .
b10000000000000000000000000000100 -
b10 ,
b10000000000000000000000000000101 +
b10000000000000000000000000000011 *
b111100000 )
b10000000000000000000000000000011 (
b0 '
b0 &
b0 %
b11100010011001100110001001101000101111101101001011011100111010000101100011100010011001100110001001101000101111101100010011010010110111000101100011100010011010100110001001100100101111101101001011011100111010000101100011100010011010100110001001100100101111101100010011010010110111000001010 $
0#
bx !
$end
#10416000
b0 7
b0 1
b0 2
b0 5
b0 8
b10000000000000 4
b0 6
b0 ;
b0 3
b0 :
b0 !
b0 9
1#
#20832000
0#
#31248000
b10000101101 '
b10000101101 0
b1000010110101 &
b1000010110101 /
b1 )
1#
#41664000
0#
#52080000
b10001001001 5
b100001001000 2
b1000010010000 7
b0 1
b1000100100111100101001000 4
b1000100100101100101001000 6
b100001001000 ;
b10000100100001 3
b10000100100001 :
b100001001000 '
b100001001000 0
b10000100100001 &
b10000100100001 /
b10 )
1#
#62496000
0#
#72912000
b1000010010000 !
b1000010010000 9
b110000111111 '
b110000111111 0
b11000011111100 &
b11000011111100 /
b11 )
1#
#83328000
0#
#93744000
b1000000000000 2
b1000000000000 5
b10000000000000 7
b0 1
b1000000000000 ;
b100000000000000 3
b100000000000010000000000000 4
b100000000000000000000000000 6
b100000000000000 :
b1000000000000 '
b1000000000000 0
b100000000000000 &
b100000000000000 /
b100 )
1#
#104160000
0#
#114576000
b10000000000000 !
b10000000000000 9
b1001101111011 '
b1001101111011 0
b100110111101100 &
b100110111101100 /
b101 )
1#
#124992000
0#
#135408000
b1011010100001 2
b10000000000000 5
b10110101000010 7
b0 1
b1011010100001 ;
b101101010000010 3
b1000000000000011011111000010 4
b1000000000000001011111000010 6
b101101010000010 :
b1011010100001 '
b1011010100001 0
b101101010000010 &
b101101010000010 /
b110 )
1#
#145824000
0#
#156240000
b10110101000010 !
b10110101000010 9
b1100101100011 '
b1100101100011 0
b110010110001101 &
b110010110001101 /
b111 )
1#
#166656000
0#
#177072000
b1101110110111 2
b10111111111111 5
b11011101101101 7
b111111111111111111 1
b1101110110110 ;
b110111011011010 3
b1011111111111110110011111100 4
b1011111111111100110011111100 6
b110111011011010 :
b1101110110110 '
b1101110110110 0
b110111011011010 &
b110111011011010 /
b1000 )
1#
#187488000
0#
#197904000
b11011101101101 !
b11011101101101 9
b1110110010000 '
b1110110010000 0
b111011001000010 &
b111011001000010 /
b1001 )
1#
#208320000
0#
#218736000
b1111011101001 2
b11101110110111 5
b11110111010010 7
b0 1
b1111011101001 ;
b111101110100011 3
b1110111011011100000101011011 4
b1110111011011010000101011011 6
b111101110100011 :
b1111011101001 '
b1111011101001 0
b111101110100011 &
b111101110100011 /
b1010 )
1#
#229152000
0#
#239568000
b11110111010010 !
b11110111010010 9
b1111110111010 '
b1111110111010 0
b111111011101000 &
b111111011101000 /
b1011 )
1#
#249984000
0#
#260400000
b10000000000000 2
b100000000000000 5
b100000000000000 7
b0 1
b10000000000000 ;
b1000000000000000 3
b10000000000000010000000000000 4
b10000000000000000000000000000 6
b1000000000000000 :
b10000000000000 '
b10000000000000 0
b1000000000000000 &
b1000000000000000 /
b1100 )
1#
#270816000
0#
#281232000
b100000000000000 !
b100000000000000 9
b1111110111010 '
b1111110111010 0
b111111011101000 &
b111111011101000 /
b1101 )
1#
#291648000
0#
#302064000
b1111011101001 2
b11101110110111 5
b11110111010010 7
b0 1
b1111011101001 ;
b111101110100011 3
b1110111011011100000101011011 4
b1110111011011010000101011011 6
b111101110100011 :
b1111011101001 '
b1111011101001 0
b111101110100011 &
b111101110100011 /
b1110 )
1#
#312480000
0#
#322896000
b11110111010010 !
b11110111010010 9
b1110110010000 '
b1110110010000 0
b111011001000010 &
b111011001000010 /
b1111 )
1#
#333312000
0#
#343728000
b1101110110111 2
b10111111111111 5
b11011101101101 7
b111111111111111111 1
b1101110110110 ;
b110111011011010 3
b1011111111111110110011111100 4
b1011111111111100110011111100 6
b110111011011010 :
b1101110110110 '
b1101110110110 0
b110111011011010 &
b110111011011010 /
b10000 )
1#
#354144000
0#
#364560000
b11011101101101 !
b11011101101101 9
b1100101100011 '
b1100101100011 0
b110010110001101 &
b110010110001101 /
b10001 )
1#
#374976000
0#
#385392000
b1011010100001 2
b10000000000000 5
b10110101000010 7
b0 1
b1011010100001 ;
b101101010000010 3
b1000000000000011011111000010 4
b1000000000000001011111000010 6
b101101010000010 :
b1011010100001 '
b1011010100001 0
b101101010000010 &
b101101010000010 /
b10010 )
1#
#395808000
0#
#406224000
b10110101000010 !
b10110101000010 9
b1001101111011 '
b1001101111011 0
b100110111101100 &
b100110111101100 /
b10011 )
1#
#416640000
0#
#427056000
b1000000000000 2
b1000000000000 5
b10000000000000 7
b0 1
b1000000000000 ;
b100000000000000 3
b100000000000010000000000000 4
b100000000000000000000000000 6
b100000000000000 :
b1000000000000 '
b1000000000000 0
b100000000000000 &
b100000000000000 /
b10100 )
1#
#437472000
0#
#447888000
b10000000000000 !
b10000000000000 9
b110000111111 '
b110000111111 0
b11000011111100 &
b11000011111100 /
b10101 )
1#
#458304000
0#
#468720000
b100001001000 2
b10001001001 5
b1000010010000 7
b0 1
b100001001000 ;
b10000100100001 3
b1000100100111100101001000 4
b1000100100101100101001000 6
b10000100100001 :
b100001001000 '
b100001001000 0
b10000100100001 &
b10000100100001 /
b10110 )
1#
#479136000
0#
#489552000
b1000010010000 !
b1000010010000 9
b10000101101 '
b10000101101 0
b1000010110101 &
b1000010110101 /
b10111 )
1#
#499968000
0#
#510384000
b0 2
b0 5
b0 7
b0 1
b0 ;
b0 3
b10000000000000 4
b0 6
b0 :
b0 '
b0 0
b0 &
b0 /
b11000 )
1#
#520800000
0#
#531216000
b0 !
b0 9
b11111101111010011 '
b11111101111010011 0
b11110111101001011 &
b11110111101001011 /
b11001 )
1#
#541632000
0#
#552048000
b10001001001 5
b11111011110111000 2
b111110111101110000 7
b0 1
b1000100100111100101001000 4
b1000100100101100101001000 6
b11111011110111000 ;
b1111101111011011111 3
b11101111011011111 :
b11111011110111000 '
b11111011110111000 0
b11101111011011111 &
b11101111011011111 /
b11010 )
1#
#562464000
0#
#572880000
b11110111101110000 !
b11110111101110000 9
b11111001111000001 '
b11111001111000001 0
b11100111100000100 &
b11100111100000100 /
b11011 )
1#
#583296000
0#
#593712000
b11111000000000000 2
b1000000000000 5
b111110000000000000 7
b0 1
b11111000000000000 ;
b1111100000000000000 3
b100000000000010000000000000 4
b100000000000000000000000000 6
b11100000000000000 :
b11111000000000000 '
b11111000000000000 0
b11100000000000000 &
b11100000000000000 /
b11100 )
1#
#604128000
0#
#614544000
b11110000000000000 !
b11110000000000000 9
b11110110010000101 '
b11110110010000101 0
b11011001000010100 &
b11011001000010100 /
b11101 )
1#
#624960000
0#
#635376000
b11110100101100000 2
b10000000000000 5
b111101001010111111 7
b111111111111111111 1
b11110100101011111 ;
b1111010010101111110 3
b1000000000000011011111000010 4
b1000000000000001011111000010 6
b11010010101111110 :
b11110100101011111 '
b11110100101011111 0
b11010010101111110 &
b11010010101111110 /
b11110 )
1#
#645792000
0#
#656208000
b11101001010111111 !
b11101001010111111 9
b11110011010011101 '
b11110011010011101 0
b11001101001110011 &
b11001101001110011 /
b11111 )
1#
#666624000
0#
#677040000
b11110010001001010 2
b10111111111111 5
b111100100010010100 7
b0 1
b11110010001001010 ;
b1111001000100100110 3
b1011111111111110110011111100 4
b1011111111111100110011111100 6
b11001000100100110 :
b11110010001001010 '
b11110010001001010 0
b11001000100100110 &
b11001000100100110 /
b100000 )
1#
#687456000
0#
#697872000
b11100100010010100 !
b11100100010010100 9
b11110001001110000 '
b11110001001110000 0
b11000100110111110 &
b11000100110111110 /
b100001 )
1#
#708288000
0#
#718704000
b11110000100010111 2
b11101110110111 5
b111100001000101110 7
b0 1
b11110000100010111 ;
b1111000010001011101 3
b1110111011011100000101011011 4
b1110111011011010000101011011 6
b11000010001011101 :
b11110000100010111 '
b11110000100010111 0
b11000010001011101 &
b11000010001011101 /
b100010 )
1#
#729120000
0#
#739536000
b11100001000101110 !
b11100001000101110 9
b11110000001000110 '
b11110000001000110 0
b11000000100011000 &
b11000000100011000 /
b100011 )
1#
#749952000
0#
#760368000
b11110000000000000 2
b100000000000000 5
b111100000000000000 7
b0 1
b11110000000000000 ;
b1111000000000000000 3
b10000000000000010000000000000 4
b10000000000000000000000000000 6
b11000000000000000 :
b11110000000000000 '
b11110000000000000 0
b11000000000000000 &
b11000000000000000 /
b100100 )
1#
#770784000
0#
#781200000
b11100000000000000 !
b11100000000000000 9
b11110000001000110 '
b11110000001000110 0
b11000000100011000 &
b11000000100011000 /
b100101 )
1#
#791616000
0#
#802032000
b11110000100010111 2
b11101110110111 5
b111100001000101110 7
b0 1
b11110000100010111 ;
b1111000010001011101 3
b1110111011011100000101011011 4
b1110111011011010000101011011 6
b11000010001011101 :
b11110000100010111 '
b11110000100010111 0
b11000010001011101 &
b11000010001011101 /
b100110 )
1#
#812448000
0#
#822864000
b11100001000101110 !
b11100001000101110 9
b11110001001110000 '
b11110001001110000 0
b11000100110111110 &
b11000100110111110 /
b100111 )
1#
#833280000
0#
#843696000
b11110010001001010 2
b10111111111111 5
b111100100010010100 7
b0 1
b11110010001001010 ;
b1111001000100100110 3
b1011111111111110110011111100 4
b1011111111111100110011111100 6
b11001000100100110 :
b11110010001001010 '
b11110010001001010 0
b11001000100100110 &
b11001000100100110 /
b101000 )
1#
#854112000
0#
#864528000
b11100100010010100 !
b11100100010010100 9
b11110011010011101 '
b11110011010011101 0
b11001101001110011 &
b11001101001110011 /
b101001 )
1#
#874944000
0#
#885360000
b11110100101100000 2
b10000000000000 5
b111101001010111111 7
b111111111111111111 1
b11110100101011111 ;
b1111010010101111110 3
b1000000000000011011111000010 4
b1000000000000001011111000010 6
b11010010101111110 :
b11110100101011111 '
b11110100101011111 0
b11010010101111110 &
b11010010101111110 /
b101010 )
1#
#895776000
0#
#906192000
b11101001010111111 !
b11101001010111111 9
b11110110010000101 '
b11110110010000101 0
b11011001000010100 &
b11011001000010100 /
b101011 )
1#
#916608000
0#
#927024000
b11111000000000000 2
b1000000000000 5
b111110000000000000 7
b0 1
b11111000000000000 ;
b1111100000000000000 3
b100000000000010000000000000 4
b100000000000000000000000000 6
b11100000000000000 :
b11111000000000000 '
b11111000000000000 0
b11100000000000000 &
b11100000000000000 /
b101100 )
1#
#937440000
0#
#947856000
b11110000000000000 !
b11110000000000000 9
b11111001111000001 '
b11111001111000001 0
b11100111100000100 &
b11100111100000100 /
b101101 )
1#
#958272000
0#
#968688000
b11111011110111000 2
b10001001001 5
b111110111101110000 7
b0 1
b11111011110111000 ;
b1111101111011011111 3
b1000100100111100101001000 4
b1000100100101100101001000 6
b11101111011011111 :
b11111011110111000 '
b11111011110111000 0
b11101111011011111 &
b11101111011011111 /
b101110 )
1#
#979104000
0#
#989520000
b11110111101110000 !
b11110111101110000 9
b11111101111010011 '
b11111101111010011 0
b11110111101001011 &
b11110111101001011 /
b101111 )
1#
#999936000
0#
#1010352000
b0 2
b0 5
b0 7
b0 1
b0 ;
b0 3
b10000000000000 4
b0 6
b0 :
b0 '
b0 0
b0 &
b0 /
b110000 )
1#
#1020768000
0#
#1031184000
b0 !
b0 9
b10000101101 '
b10000101101 0
b1000010110101 &
b1000010110101 /
b110001 )
1#
#1041600000
0#
#1052016000
b10001001001 5
b100001001000 2
b1000010010000 7
b0 1
b1000100100111100101001000 4
b1000100100101100101001000 6
b100001001000 ;
b10000100100001 3
b10000100100001 :
b100001001000 '
b100001001000 0
b10000100100001 &
b10000100100001 /
b110010 )
1#
#1062432000
0#
#1072848000
b1000010010000 !
b1000010010000 9
b110000111111 '
b110000111111 0
b11000011111100 &
b11000011111100 /
b110011 )
1#
#1083264000
0#
#1093680000
b1000000000000 2
b1000000000000 5
b10000000000000 7
b0 1
b1000000000000 ;
b100000000000000 3
b100000000000010000000000000 4
b100000000000000000000000000 6
b100000000000000 :
b1000000000000 '
b1000000000000 0
b100000000000000 &
b100000000000000 /
b110100 )
1#
#1104096000
0#
#1114512000
b10000000000000 !
b10000000000000 9
b1001101111011 '
b1001101111011 0
b100110111101100 &
b100110111101100 /
b110101 )
1#
#1124928000
0#
#1135344000
b1011010100001 2
b10000000000000 5
b10110101000010 7
b0 1
b1011010100001 ;
b101101010000010 3
b1000000000000011011111000010 4
b1000000000000001011111000010 6
b101101010000010 :
b1011010100001 '
b1011010100001 0
b101101010000010 &
b101101010000010 /
b110110 )
1#
#1145760000
0#
#1156176000
b10110101000010 !
b10110101000010 9
b1100101100011 '
b1100101100011 0
b110010110001101 &
b110010110001101 /
b110111 )
1#
#1166592000
0#
#1177008000
b1101110110111 2
b10111111111111 5
b11011101101101 7
b111111111111111111 1
b1101110110110 ;
b110111011011010 3
b1011111111111110110011111100 4
b1011111111111100110011111100 6
b110111011011010 :
b1101110110110 '
b1101110110110 0
b110111011011010 &
b110111011011010 /
b111000 )
1#
#1187424000
0#
#1197840000
b11011101101101 !
b11011101101101 9
b1110110010000 '
b1110110010000 0
b111011001000010 &
b111011001000010 /
b111001 )
1#
#1208256000
0#
#1218672000
b1111011101001 2
b11101110110111 5
b11110111010010 7
b0 1
b1111011101001 ;
b111101110100011 3
b1110111011011100000101011011 4
b1110111011011010000101011011 6
b111101110100011 :
b1111011101001 '
b1111011101001 0
b111101110100011 &
b111101110100011 /
b111010 )
1#
#1229088000
0#
#1239504000
b11110111010010 !
b11110111010010 9
b1111110111010 '
b1111110111010 0
b111111011101000 &
b111111011101000 /
b111011 )
1#
#1249920000
0#
#1260336000
b10000000000000 2
b100000000000000 5
b100000000000000 7
b0 1
b10000000000000 ;
b1000000000000000 3
b10000000000000010000000000000 4
b10000000000000000000000000000 6
b1000000000000000 :
b10000000000000 '
b10000000000000 0
b1000000000000000 &
b1000000000000000 /
b111100 )
1#
#1270752000
0#
#1281168000
b100000000000000 !
b100000000000000 9
b1111110111010 '
b1111110111010 0
b111111011101000 &
b111111011101000 /
b111101 )
1#
#1291584000
0#
#1302000000
b1111011101001 2
b11101110110111 5
b11110111010010 7
b0 1
b1111011101001 ;
b111101110100011 3
b1110111011011100000101011011 4
b1110111011011010000101011011 6
b111101110100011 :
b1111011101001 '
b1111011101001 0
b111101110100011 &
b111101110100011 /
b111110 )
1#
#1312416000
0#
#1322832000
b11110111010010 !
b11110111010010 9
b1110110010000 '
b1110110010000 0
b111011001000010 &
b111011001000010 /
b111111 )
1#
#1333248000
0#
#1343664000
b1101110110111 2
b10111111111111 5
b11011101101101 7
b111111111111111111 1
b1101110110110 ;
b110111011011010 3
b1011111111111110110011111100 4
b1011111111111100110011111100 6
b110111011011010 :
b1101110110110 '
b1101110110110 0
b110111011011010 &
b110111011011010 /
b1000000 )
1#
#1354080000
0#
#1364496000
b11011101101101 !
b11011101101101 9
b1100101100011 '
b1100101100011 0
b110010110001101 &
b110010110001101 /
b1000001 )
1#
#1374912000
0#
#1385328000
b1011010100001 2
b10000000000000 5
b10110101000010 7
b0 1
b1011010100001 ;
b101101010000010 3
b1000000000000011011111000010 4
b1000000000000001011111000010 6
b101101010000010 :
b1011010100001 '
b1011010100001 0
b101101010000010 &
b101101010000010 /
b1000010 )
1#
#1395744000
0#
#1406160000
b10110101000010 !
b10110101000010 9
b1001101111011 '
b1001101111011 0
b100110111101100 &
b100110111101100 /
b1000011 )
1#
#1416576000
0#
#1426992000
b1000000000000 2
b1000000000000 5
b10000000000000 7
b0 1
b1000000000000 ;
b100000000000000 3
b100000000000010000000000000 4
b100000000000000000000000000 6
b100000000000000 :
b1000000000000 '
b1000000000000 0
b100000000000000 &
b100000000000000 /
b1000100 )
1#
#1437408000
0#
#1447824000
b10000000000000 !
b10000000000000 9
b110000111111 '
b110000111111 0
b11000011111100 &
b11000011111100 /
b1000101 )
1#
#1458240000
0#
#1468656000
b100001001000 2
b10001001001 5
b1000010010000 7
b0 1
b100001001000 ;
b10000100100001 3
b1000100100111100101001000 4
b1000100100101100101001000 6
b10000100100001 :
b100001001000 '
b100001001000 0
b10000100100001 &
b10000100100001 /
b1000110 )
1#
#1479072000
0#
#1489488000
b1000010010000 !
b1000010010000 9
b10000101101 '
b10000101101 0
b1000010110101 &
b1000010110101 /
b1000111 )
1#
#1499904000
0#
#1510320000
b0 2
b0 5
b0 7
b0 1
b0 ;
b0 3
b10000000000000 4
b0 6
b0 :
b0 '
b0 0
b0 &
b0 /
b1001000 )
1#
#1520736000
0#
#1531152000
b0 !
b0 9
b11111101111010011 '
b11111101111010011 0
b11110111101001011 &
b11110111101001011 /
b1001001 )
1#
#1541568000
0#
#1551984000
b10001001001 5
b11111011110111000 2
b111110111101110000 7
b0 1
b1000100100111100101001000 4
b1000100100101100101001000 6
b11111011110111000 ;
b1111101111011011111 3
b11101111011011111 :
b11111011110111000 '
b11111011110111000 0
b11101111011011111 &
b11101111011011111 /
b1001010 )
1#
#1562400000
0#
#1572816000
b11110111101110000 !
b11110111101110000 9
b11111001111000001 '
b11111001111000001 0
b11100111100000100 &
b11100111100000100 /
b1001011 )
1#
#1583232000
0#
#1593648000
b11111000000000000 2
b1000000000000 5
b111110000000000000 7
b0 1
b11111000000000000 ;
b1111100000000000000 3
b100000000000010000000000000 4
b100000000000000000000000000 6
b11100000000000000 :
b11111000000000000 '
b11111000000000000 0
b11100000000000000 &
b11100000000000000 /
b1001100 )
1#
#1604064000
0#
#1614480000
b11110000000000000 !
b11110000000000000 9
b11110110010000101 '
b11110110010000101 0
b11011001000010100 &
b11011001000010100 /
b1001101 )
1#
#1624896000
0#
#1635312000
b11110100101100000 2
b10000000000000 5
b111101001010111111 7
b111111111111111111 1
b11110100101011111 ;
b1111010010101111110 3
b1000000000000011011111000010 4
b1000000000000001011111000010 6
b11010010101111110 :
b11110100101011111 '
b11110100101011111 0
b11010010101111110 &
b11010010101111110 /
b1001110 )
1#
#1645728000
0#
#1656144000
b11101001010111111 !
b11101001010111111 9
b11110011010011101 '
b11110011010011101 0
b11001101001110011 &
b11001101001110011 /
b1001111 )
1#
#1666560000
0#
#1676976000
b11110010001001010 2
b10111111111111 5
b111100100010010100 7
b0 1
b11110010001001010 ;
b1111001000100100110 3
b1011111111111110110011111100 4
b1011111111111100110011111100 6
b11001000100100110 :
b11110010001001010 '
b11110010001001010 0
b11001000100100110 &
b11001000100100110 /
b1010000 )
1#
#1687392000
0#
#1697808000
b11100100010010100 !
b11100100010010100 9
b11110001001110000 '
b11110001001110000 0
b11000100110111110 &
b11000100110111110 /
b1010001 )
1#
#1708224000
0#
#1718640000
b11110000100010111 2
b11101110110111 5
b111100001000101110 7
b0 1
b11110000100010111 ;
b1111000010001011101 3
b1110111011011100000101011011 4
b1110111011011010000101011011 6
b11000010001011101 :
b11110000100010111 '
b11110000100010111 0
b11000010001011101 &
b11000010001011101 /
b1010010 )
1#
#1729056000
0#
#1739472000
b11100001000101110 !
b11100001000101110 9
b11110000001000110 '
b11110000001000110 0
b11000000100011000 &
b11000000100011000 /
b1010011 )
1#
#1749888000
0#
#1760304000
b11110000000000000 2
b100000000000000 5
b111100000000000000 7
b0 1
b11110000000000000 ;
b1111000000000000000 3
b10000000000000010000000000000 4
b10000000000000000000000000000 6
b11000000000000000 :
b11110000000000000 '
b11110000000000000 0
b11000000000000000 &
b11000000000000000 /
b1010100 )
1#
#1770720000
0#
#1781136000
b11100000000000000 !
b11100000000000000 9
b11110000001000110 '
b11110000001000110 0
b11000000100011000 &
b11000000100011000 /
b1010101 )
1#
#1791552000
0#
#1801968000
b11110000100010111 2
b11101110110111 5
b111100001000101110 7
b0 1
b11110000100010111 ;
b1111000010001011101 3
b1110111011011100000101011011 4
b1110111011011010000101011011 6
b11000010001011101 :
b11110000100010111 '
b11110000100010111 0
b11000010001011101 &
b11000010001011101 /
b1010110 )
1#
#1812384000
0#
#1822800000
b11100001000101110 !
b11100001000101110 9
b11110001001110000 '
b11110001001110000 0
b11000100110111110 &
b11000100110111110 /
b1010111 )
1#
#1833216000
0#
#1843632000
b11110010001001010 2
b10111111111111 5
b111100100010010100 7
b0 1
b11110010001001010 ;
b1111001000100100110 3
b1011111111111110110011111100 4
b1011111111111100110011111100 6
b11001000100100110 :
b11110010001001010 '
b11110010001001010 0
b11001000100100110 &
b11001000100100110 /
b1011000 )
1#
#1854048000
0#
#1864464000
b11100100010010100 !
b11100100010010100 9
b11110011010011101 '
b11110011010011101 0
b11001101001110011 &
b11001101001110011 /
b1011001 )
1#
#1874880000
0#
#1885296000
b11110100101100000 2
b10000000000000 5
b111101001010111111 7
b111111111111111111 1
b11110100101011111 ;
b1111010010101111110 3
b1000000000000011011111000010 4
b1000000000000001011111000010 6
b11010010101111110 :
b11110100101011111 '
b11110100101011111 0
b11010010101111110 &
b11010010101111110 /
b1011010 )
1#
#1895712000
0#
#1906128000
b11101001010111111 !
b11101001010111111 9
b11110110010000101 '
b11110110010000101 0
b11011001000010100 &
b11011001000010100 /
b1011011 )
1#
#1916544000
0#
#1926960000
b11111000000000000 2
b1000000000000 5
b111110000000000000 7
b0 1
b11111000000000000 ;
b1111100000000000000 3
b100000000000010000000000000 4
b100000000000000000000000000 6
b11100000000000000 :
b11111000000000000 '
b11111000000000000 0
b11100000000000000 &
b11100000000000000 /
b1011100 )
1#
#1937376000
0#
#1947792000
b11110000000000000 !
b11110000000000000 9
b11111001111000001 '
b11111001111000001 0
b11100111100000100 &
b11100111100000100 /
b1011101 )
1#
#1958208000
0#
#1968624000
b11111011110111000 2
b10001001001 5
b111110111101110000 7
b0 1
b11111011110111000 ;
b1111101111011011111 3
b1000100100111100101001000 4
b1000100100101100101001000 6
b11101111011011111 :
b11111011110111000 '
b11111011110111000 0
b11101111011011111 &
b11101111011011111 /
b1011110 )
1#
#1979040000
0#
#1989456000
b11110111101110000 !
b11110111101110000 9
b11111101111010011 '
b11111101111010011 0
b11110111101001011 &
b11110111101001011 /
b1011111 )
1#
#1999872000
0#
#2010288000
b0 2
b0 5
b0 7
b0 1
b0 ;
b0 3
b10000000000000 4
b0 6
b0 :
b0 '
b0 0
b0 &
b0 /
b1100000 )
1#
#2020704000
0#
#2031120000
b0 !
b0 9
b10000101101 '
b10000101101 0
b1000010110101 &
b1000010110101 /
b1100001 )
1#
#2041536000
0#
#2051952000
b10001001001 5
b100001001000 2
b1000010010000 7
b0 1
b1000100100111100101001000 4
b1000100100101100101001000 6
b100001001000 ;
b10000100100001 3
b10000100100001 :
b100001001000 '
b100001001000 0
b10000100100001 &
b10000100100001 /
b1100010 )
1#
#2062368000
0#
#2072784000
b1000010010000 !
b1000010010000 9
b110000111111 '
b110000111111 0
b11000011111100 &
b11000011111100 /
b1100011 )
1#
#2083200000
0#
#2093616000
b1000000000000 2
b1000000000000 5
b10000000000000 7
b0 1
b1000000000000 ;
b100000000000000 3
b100000000000010000000000000 4
b100000000000000000000000000 6
b100000000000000 :
b1000000000000 '
b1000000000000 0
b100000000000000 &
b100000000000000 /
b1100100 )
1#
#2104032000
0#
#2114448000
b10000000000000 !
b10000000000000 9
b1001101111011 '
b1001101111011 0
b100110111101100 &
b100110111101100 /
b1100101 )
1#
#2124864000
0#
#2135280000
b1011010100001 2
b10000000000000 5
b10110101000010 7
b0 1
b1011010100001 ;
b101101010000010 3
b1000000000000011011111000010 4
b1000000000000001011111000010 6
b101101010000010 :
b1011010100001 '
b1011010100001 0
b101101010000010 &
b101101010000010 /
b1100110 )
1#
#2145696000
0#
#2156112000
b10110101000010 !
b10110101000010 9
b1100101100011 '
b1100101100011 0
b110010110001101 &
b110010110001101 /
b1100111 )
1#
#2166528000
0#
