Verilog Projects/fft8/fft8_stage3.v
`timescale 1ns/1ps
module fft8_stage3 (
    input clk,
    input rst,

    // inputs from Stage-2
    input signed [10:0] sum_in1_r, sum_in1_i,
    input signed [10:0] sum_in2_r, sum_in2_i,
    input signed [10:0] diff_in1_r, diff_in1_i,
    input signed [10:0] diff_in2_r, diff_in2_i,
    input valid_in,

    // outputs
    output reg signed [12:0] X0_r, X0_i,
    output reg signed [12:0] X4_r, X4_i,
    output reg signed [12:0] X2_r, X2_i,
    output reg signed [12:0] X6_r, X6_i,
    output reg valid_out
);

    // ============================
    // Pair selector
    // ============================
    reg pair_cnt;

    // ============================
    // Twiddle factors (Q1.7)
    // ============================
    reg signed [7:0] wr1, wi1;
    reg signed [7:0] wr2, wi2;

    always @(*) begin
        case(pair_cnt)
            1'b0: begin
                wr1 = 8'sd127;  wi1 = 8'sd0;     // W0
                wr2 = 8'sd0;    wi2 = -8'sd127;  // W2
            end
            1'b1: begin
                wr1 = 8'sd91;   wi1 = -8'sd91;   // W1
                wr2 = -8'sd91;  wi2 = -8'sd91;   // W3
            end
        endcase
    end

    // ============================
    // Complex Multiply (scaled once)
    // ============================
    wire signed [18:0] mult1_r, mult1_i;
    wire signed [18:0] mult2_r, mult2_i;

    assign mult1_r = (diff_in1_r * wr1 - diff_in1_i * wi1) >>> 7;
    assign mult1_i = (diff_in1_r * wi1 + diff_in1_i * wr1) >>> 7;

    assign mult2_r = (diff_in2_r * wr2 - diff_in2_i * wi2) >>> 7;
    assign mult2_i = (diff_in2_r * wi2 + diff_in2_i * wr2) >>> 7;

    // ============================
    // Trim to 13-bit (NO extra scaling)
    // ============================
    wire signed [12:0] m1_r_s, m1_i_s;
    wire signed [12:0] m2_r_s, m2_i_s;

    assign m1_r_s = mult1_r[12:0];
    assign m1_i_s = mult1_i[12:0];
    assign m2_r_s = mult2_r[12:0];
    assign m2_i_s = mult2_i[12:0];

    // ============================
    // Sign Extension of inputs
    // ============================
    wire signed [12:0] s1_r, s1_i;
    wire signed [12:0] s2_r, s2_i;

    assign s1_r = { {2{sum_in1_r[10]}}, sum_in1_r };
    assign s1_i = { {2{sum_in1_i[10]}}, sum_in1_i };

    assign s2_r = { {2{sum_in2_r[10]}}, sum_in2_r };
    assign s2_i = { {2{sum_in2_i[10]}}, sum_in2_i };

    // ============================
    // Output logic
    // ============================
    always @(posedge clk or posedge rst) begin
        if (rst) begin
            X0_r <= 0; X0_i <= 0;
            X4_r <= 0; X4_i <= 0;
            X2_r <= 0; X2_i <= 0;
            X6_r <= 0; X6_i <= 0;
            valid_out <= 0;
            pair_cnt <= 0;
        end else begin
            valid_out <= 0;

            if (valid_in) begin

                // FFT butterfly
                X0_r <= s1_r + m1_r_s;
                X0_i <= s1_i + m1_i_s;

                X4_r <= s1_r - m1_r_s;
                X4_i <= s1_i - m1_i_s;

                X2_r <= s2_r + m2_r_s;
                X2_i <= s2_i + m2_i_s;

                X6_r <= s2_r - m2_r_s;
                X6_i <= s2_i - m2_i_s;

                valid_out <= 1;

                // Toggle pair
                pair_cnt <= ~pair_cnt;
            end
        end
    end

endmodule

Verilog Projects/fft8/fft8_stage2.v
`timescale 1ns/1ps
module fft8_stage2(
    input clk,
    input rst,

    input signed [8:0] sum_in_r, sum_in_i,    // y0..y3
    input signed [8:0] diff_in_r, diff_in_i,  // y4..y7
    input valid_in,

    output reg signed [10:0] sum1_r, sum1_i,
    output reg signed [10:0] sum2_r, sum2_i,
    output reg signed [10:0] diff1_r, diff1_i,
    output reg signed [10:0] diff2_r, diff2_i,
    output reg valid_out
);

    // ============================
    // Memory to store first two inputs
    // ============================
    reg signed [8:0] sum_mem_r[0:1];   // y0, y1
    reg signed [8:0] sum_mem_i[0:1];
    reg signed [8:0] diff_mem_r[0:1];  // y4, y5
    reg signed [8:0] diff_mem_i[0:1];

    reg [1:0] count;  // counts 0..3

    always @(posedge clk or posedge rst) begin
        if(rst) begin
            count <= 0;
            valid_out <= 0;
            {sum1_r,sum1_i,sum2_r,sum2_i,
             diff1_r,diff1_i,diff2_r,diff2_i} <= 0;
        end else begin
            valid_out <= 0;

            if(valid_in) begin
                case(count)
                    2'd0: begin
                        // store y0 and y4
                        sum_mem_r[0]  <= sum_in_r;
                        sum_mem_i[0]  <= sum_in_i;
                        diff_mem_r[0] <= diff_in_r;
                        diff_mem_i[0] <= diff_in_i;
                    end
                    2'd1: begin
                        // store y1 and y5
                        sum_mem_r[1]  <= sum_in_r;
                        sum_mem_i[1]  <= sum_in_i;
                        diff_mem_r[1] <= diff_in_r;
                        diff_mem_i[1] <= diff_in_i;
                    end
                    2'd2: begin
                        // compute first pair outputs (z0, z2, z4, z6)
                        sum1_r  <= sum_mem_r[0] + sum_in_r; // z0 = y0 + y2
                        sum1_i  <= sum_mem_i[0] + sum_in_i;

                        sum2_r  <= sum_mem_r[0] - sum_in_r; // z2 = y0 - y2
                        sum2_i  <= sum_mem_i[0] - sum_in_i;

                        diff1_r <= diff_mem_r[0] + diff_in_i;  // z4 = y4 + (-j)*y6
                        diff1_i <= diff_mem_i[0] - diff_in_r;

                        diff2_r <= diff_mem_r[0] - diff_in_i;  // z6 = y4 - (-j)*y6
                        diff2_i <= diff_mem_i[0] + diff_in_r;

                        valid_out <= 1;
                    end
                    2'd3: begin
                        // compute second pair outputs (z1, z3, z5, z7)
                        sum1_r  <= sum_mem_r[1] + sum_in_r; // z1 = y1 + y3
                        sum1_i  <= sum_mem_i[1] + sum_in_i;

                        sum2_r  <= sum_mem_r[1] - sum_in_r; // z3 = y1 - y3
                        sum2_i  <= sum_mem_i[1] - sum_in_i;

                        diff1_r <= diff_mem_r[1] + diff_in_i; // z5 = y5 + (-j)*y7
                        diff1_i <= diff_mem_i[1] - diff_in_r;

                        diff2_r <= diff_mem_r[1] - diff_in_i; // z7 = y5 - (-j)*y7
                        diff2_i <= diff_mem_i[1] + diff_in_r;

                        valid_out <= 1;
                    end
                endcase

                count <= count + 2'd1;
            end
        end
    end

endmodule

Verilog Projects/fft8/fft8_stage1.v
`timescale 1ns/1ps

module fft8_stage1 (
    input clk,
    input rst,
    input signed [7:0] xr, xi,
    input valid_in,

    output reg signed [8:0] sum_r, sum_i,
    output reg signed [8:0] diff_r, diff_i,
    output reg valid_out
);

// ============================
// Memory (store first 4 samples)
// ============================
reg signed [7:0] mem_r [0:3];
reg signed [7:0] mem_i [0:3];

reg [2:0] count;

// pipeline regs
reg signed [7:0] a_r, a_i;
reg signed [7:0] b_r, b_i;
reg valid_d;

// ============================
// Main logic
// ============================
always @(posedge clk or posedge rst) begin
    if (rst) begin
        count <= 0;
        valid_out <= 0;
        valid_d <= 0;
    end else begin
        valid_out <= 0;
        valid_d <= 0;

        if (valid_in) begin
            if (count < 4) begin
                // store first 4
                mem_r[count] <= xr;
                mem_i[count] <= xi;
            end else begin
                // fetch pair
                a_r <= mem_r[count - 4];
                a_i <= mem_i[count - 4];

                b_r <= xr;
                b_i <= xi;

                valid_d <= 1;
            end

            count <= count + 3'd1;
        end

        // compute butterfly (same cycle output)
        if (valid_d) begin
            sum_r  <= a_r + b_r;
            sum_i  <= a_i + b_i;

            diff_r <= a_r - b_r;
            diff_i <= a_i - b_i;

            valid_out <= 1;
        end
    end
end

endmodule

Verilog Projects/fft8/fft8_wrapper.v
`timescale 1ns/1ps
module fft8_wrapper(
    input clk,
    input rst,
    input signed [7:0] xr,
    input signed [7:0] xi,
    input valid_in,

    output signed [12:0] X0_r, X0_i,
    output signed [12:0] X4_r, X4_i,
    output signed [12:0] X2_r, X2_i,
    output signed [12:0] X6_r, X6_i,
    output valid_out
);

    // ============================
    // Stage-1 outputs
    // ============================
    wire signed [8:0] s1_sum_r, s1_sum_i;
    wire signed [8:0] s1_diff_r, s1_diff_i;
    wire s1_valid;

    fft8_stage1 stage1 (
        .clk(clk),
        .rst(rst),
        .xr(xr),
        .xi(xi),
        .valid_in(valid_in),
        .sum_r(s1_sum_r),
        .sum_i(s1_sum_i),
        .diff_r(s1_diff_r),
        .diff_i(s1_diff_i),
        .valid_out(s1_valid)
    );

    // ============================
    // Stage-2 outputs (pairwise)
    // ============================
    wire signed [10:0] s2_sum1_r, s2_sum1_i;
    wire signed [10:0] s2_sum2_r, s2_sum2_i;
    wire signed [10:0] s2_diff1_r, s2_diff1_i;
    wire signed [10:0] s2_diff2_r, s2_diff2_i;
    wire s2_valid;

    fft8_stage2 stage2 (
        .clk(clk),
        .rst(rst),
        .sum_in_r(s1_sum_r),
        .sum_in_i(s1_sum_i),
        .diff_in_r(s1_diff_r),
        .diff_in_i(s1_diff_i),
        .valid_in(s1_valid),
        .sum1_r(s2_sum1_r),
        .sum1_i(s2_sum1_i),
        .sum2_r(s2_sum2_r),
        .sum2_i(s2_sum2_i),
        .diff1_r(s2_diff1_r),
        .diff1_i(s2_diff1_i),
        .diff2_r(s2_diff2_r),
        .diff2_i(s2_diff2_i),
        .valid_out(s2_valid)
    );

    // ============================
    // Stage-3 outputs
    // ============================
    fft8_stage3 stage3 (
        .clk(clk),
        .rst(rst),
        .sum_in1_r(s2_sum1_r),
        .sum_in1_i(s2_sum1_i),
        .sum_in2_r(s2_sum2_r),
        .sum_in2_i(s2_sum2_i),
        .diff_in1_r(s2_diff1_r),
        .diff_in1_i(s2_diff1_i),
        .diff_in2_r(s2_diff2_r),
        .diff_in2_i(s2_diff2_i),
        .valid_in(s2_valid),
        .X0_r(X0_r),
        .X0_i(X0_i),
        .X4_r(X4_r),
        .X4_i(X4_i),
        .X2_r(X2_r),
        .X2_i(X2_i),
        .X6_r(X6_r),
        .X6_i(X6_i),
        .valid_out(valid_out)
    );

endmodule

Verilog Projects/fft8/tb_fft8_wrapper.v
`timescale 1ns/1ps
module tb_fft8_wrapper;

    reg clk;
    reg rst;
    reg signed [7:0] xr, xi;
    reg valid_in;

    // ============================
    // Wrapper outputs
    // ============================
    wire signed [12:0] X0_r, X0_i;
    wire signed [12:0] X4_r, X4_i;
    wire signed [12:0] X2_r, X2_i;
    wire signed [12:0] X6_r, X6_i;
    wire valid_out;

    // ============================
    // Instantiate Wrapper
    // ============================
    fft8_wrapper fft_wrap (
        .clk(clk),
        .rst(rst),
        .xr(xr),
        .xi(xi),
        .valid_in(valid_in),
        .X0_r(X0_r),
        .X0_i(X0_i),
        .X4_r(X4_r),
        .X4_i(X4_i),
        .X2_r(X2_r),
        .X2_i(X2_i),
        .X6_r(X6_r),
        .X6_i(X6_i),
        .valid_out(valid_out)
    );

    // ============================
    // Clock
    // ============================
    always #5 clk = ~clk;

    // ============================
    // File I/O
    // ============================
    integer fr_real, fr_imag;
    integer fout;
    integer status_r, status_i;
    integer i;

    // ============================
    // Output storage
    // ============================
    reg signed [12:0] out_r [0:7];
    reg signed [12:0] out_i [0:7];
    reg valid_cycle_count; // 0 → first, 1 → second

    // ============================
    // VCD
    // ============================
    initial begin
        $dumpfile("fft8_wrapper.vcd");
        $dumpvars(0, tb_fft8_wrapper);
    end

    // ============================
    // Stimulus
    // ============================
    initial begin
        clk = 0;
        rst = 1;
        valid_in = 0;
        xr = 0;
        xi = 0;
        valid_cycle_count = 0;

        fout = $fopen("fft8_output_ordered.mem", "w");

        fr_real = $fopen("input_real.mem", "r");
        fr_imag = $fopen("input_imag.mem", "r");

        if (fr_real == 0 || fr_imag == 0) begin
            $display("ERROR opening input files");
            $finish;
        end

        // Reset
        #20;
        rst = 0;

        // Start input
        #10;
        valid_in = 1;

        // Feed 8 samples
        for (i = 0; i < 8; i = i + 1) begin
            status_r = $fscanf(fr_real, "%d\n", xr);
            status_i = $fscanf(fr_imag, "%d\n", xi);

            if (status_r != 1 || status_i != 1)
                $display("ERROR reading input at %0d", i);

            #10;
        end

        valid_in = 0;
        xr = 0;
        xi = 0;

        // wait for pipeline
        #300;

        $display("TIMEOUT - No complete FFT captured");
        $finish;
    end

    // ============================
    // Capture outputs (CORRECTED)
    // ============================
    always @(posedge clk) begin
        if (valid_out) begin

            if (valid_cycle_count == 0) begin
                // FIRST valid → X0,X2,X4,X6
                out_r[0] <= X0_r; out_i[0] <= X0_i;
                out_r[2] <= X2_r; out_i[2] <= X2_i;
                out_r[4] <= X4_r; out_i[4] <= X4_i;
                out_r[6] <= X6_r; out_i[6] <= X6_i;

                valid_cycle_count <= 1;
            end
            else begin
                // SECOND valid → X1,X3,X5,X7
                out_r[1] <= X0_r; out_i[1] <= X0_i;
                out_r[3] <= X2_r; out_i[3] <= X2_i;
                out_r[5] <= X4_r; out_i[5] <= X4_i;
                out_r[7] <= X6_r; out_i[7] <= X6_i;

                // small delay to ensure values settle
                #1;

                // write outputs
                for (i = 0; i < 8; i = i + 1) begin
                    $fwrite(fout, "%d %d\n", out_r[i], out_i[i]);
                    $display("X[%0d] = (%d,%d)", i, out_r[i], out_i[i]);
                end

                valid_cycle_count <= 0;

                $fclose(fout);
                $finish;
            end
        end
    end

endmodule

Verilog Projects/fft8/fft8_wrapper.vcd
$date
	Wed Apr 22 15:09:36 2026
$end
$version
	Icarus Verilog
$end
$timescale
	1ps
$end
$scope module tb_fft8_wrapper $end
$var wire 1 ! valid_out $end
$var wire 13 " X6_r [12:0] $end
$var wire 13 # X6_i [12:0] $end
$var wire 13 $ X4_r [12:0] $end
$var wire 13 % X4_i [12:0] $end
$var wire 13 & X2_r [12:0] $end
$var wire 13 ' X2_i [12:0] $end
$var wire 13 ( X0_r [12:0] $end
$var wire 13 ) X0_i [12:0] $end
$var reg 1 * clk $end
$var reg 1 + rst $end
$var reg 1 , valid_cycle_count $end
$var reg 1 - valid_in $end
$var reg 8 . xi [7:0] $end
$var reg 8 / xr [7:0] $end
$var integer 32 0 fout [31:0] $end
$var integer 32 1 fr_imag [31:0] $end
$var integer 32 2 fr_real [31:0] $end
$var integer 32 3 i [31:0] $end
$var integer 32 4 status_i [31:0] $end
$var integer 32 5 status_r [31:0] $end
$scope module fft_wrap $end
$var wire 1 * clk $end
$var wire 1 + rst $end
$var wire 1 - valid_in $end
$var wire 8 6 xi [7:0] $end
$var wire 8 7 xr [7:0] $end
$var wire 1 ! valid_out $end
$var wire 1 8 s2_valid $end
$var wire 11 9 s2_sum2_r [10:0] $end
$var wire 11 : s2_sum2_i [10:0] $end
$var wire 11 ; s2_sum1_r [10:0] $end
$var wire 11 < s2_sum1_i [10:0] $end
$var wire 11 = s2_diff2_r [10:0] $end
$var wire 11 > s2_diff2_i [10:0] $end
$var wire 11 ? s2_diff1_r [10:0] $end
$var wire 11 @ s2_diff1_i [10:0] $end
$var wire 1 A s1_valid $end
$var wire 9 B s1_sum_r [8:0] $end
$var wire 9 C s1_sum_i [8:0] $end
$var wire 9 D s1_diff_r [8:0] $end
$var wire 9 E s1_diff_i [8:0] $end
$var wire 13 F X6_r [12:0] $end
$var wire 13 G X6_i [12:0] $end
$var wire 13 H X4_r [12:0] $end
$var wire 13 I X4_i [12:0] $end
$var wire 13 J X2_r [12:0] $end
$var wire 13 K X2_i [12:0] $end
$var wire 13 L X0_r [12:0] $end
$var wire 13 M X0_i [12:0] $end
$scope module stage1 $end
$var wire 1 * clk $end
$var wire 1 + rst $end
$var wire 1 - valid_in $end
$var wire 8 N xi [7:0] $end
$var wire 8 O xr [7:0] $end
$var reg 8 P a_i [7:0] $end
$var reg 8 Q a_r [7:0] $end
$var reg 8 R b_i [7:0] $end
$var reg 8 S b_r [7:0] $end
$var reg 3 T count [2:0] $end
$var reg 9 U diff_i [8:0] $end
$var reg 9 V diff_r [8:0] $end
$var reg 9 W sum_i [8:0] $end
$var reg 9 X sum_r [8:0] $end
$var reg 1 Y valid_d $end
$var reg 1 A valid_out $end
$upscope $end
$scope module stage2 $end
$var wire 1 * clk $end
$var wire 9 Z diff_in_i [8:0] $end
$var wire 9 [ diff_in_r [8:0] $end
$var wire 1 + rst $end
$var wire 9 \ sum_in_i [8:0] $end
$var wire 9 ] sum_in_r [8:0] $end
$var wire 1 A valid_in $end
$var reg 2 ^ count [1:0] $end
$var reg 11 _ diff1_i [10:0] $end
$var reg 11 ` diff1_r [10:0] $end
$var reg 11 a diff2_i [10:0] $end
$var reg 11 b diff2_r [10:0] $end
$var reg 11 c sum1_i [10:0] $end
$var reg 11 d sum1_r [10:0] $end
$var reg 11 e sum2_i [10:0] $end
$var reg 11 f sum2_r [10:0] $end
$var reg 1 8 valid_out $end
$upscope $end
$scope module stage3 $end
$var wire 1 * clk $end
$var wire 11 g diff_in1_i [10:0] $end
$var wire 11 h diff_in1_r [10:0] $end
$var wire 11 i diff_in2_i [10:0] $end
$var wire 11 j diff_in2_r [10:0] $end
$var wire 1 + rst $end
$var wire 11 k sum_in1_i [10:0] $end
$var wire 11 l sum_in1_r [10:0] $end
$var wire 11 m sum_in2_i [10:0] $end
$var wire 11 n sum_in2_r [10:0] $end
$var wire 1 8 valid_in $end
$var wire 13 o s2_r [12:0] $end
$var wire 13 p s2_i [12:0] $end
$var wire 13 q s1_r [12:0] $end
$var wire 13 r s1_i [12:0] $end
$var wire 19 s mult2_r [18:0] $end
$var wire 19 t mult2_i [18:0] $end
$var wire 19 u mult1_r [18:0] $end
$var wire 19 v mult1_i [18:0] $end
$var wire 13 w m2_r_s [12:0] $end
$var wire 13 x m2_i_s [12:0] $end
$var wire 13 y m1_r_s [12:0] $end
$var wire 13 z m1_i_s [12:0] $end
$var reg 13 { X0_i [12:0] $end
$var reg 13 | X0_r [12:0] $end
$var reg 13 } X2_i [12:0] $end
$var reg 13 ~ X2_r [12:0] $end
$var reg 13 !" X4_i [12:0] $end
$var reg 13 "" X4_r [12:0] $end
$var reg 13 #" X6_i [12:0] $end
$var reg 13 $" X6_r [12:0] $end
$var reg 1 %" pair_cnt $end
$var reg 1 ! valid_out $end
$var reg 8 &" wi1 [7:0] $end
$var reg 8 '" wi2 [7:0] $end
$var reg 8 (" wr1 [7:0] $end
$var reg 8 )" wr2 [7:0] $end
$upscope $end
$upscope $end
$upscope $end
$enddefinitions $end
$comment Show the parameter values. $end
$dumpall
$end
#0
$dumpvars
b0 )"
b1111111 ("
b10000001 '"
b0 &"
0%"
b0 $"
b0 #"
b0 ""
b0 !"
b0 ~
b0 }
b0 |
b0 {
b0 z
b0 y
b0 x
b0 w
b0 v
b0 u
b0 t
b0 s
b0 r
b0 q
b0 p
b0 o
b0 n
b0 m
b0 l
b0 k
b0 j
b0 i
b0 h
b0 g
b0 f
b0 e
b0 d
b0 c
b0 b
b0 a
b0 `
b0 _
b0 ^
bx ]
bx \
bx [
bx Z
0Y
bx X
bx W
bx V
bx U
b0 T
bx S
bx R
bx Q
bx P
b0 O
b0 N
b0 M
b0 L
b0 K
b0 J
b0 I
b0 H
b0 G
b0 F
bx E
bx D
bx C
bx B
0A
b0 @
b0 ?
b0 >
b0 =
b0 <
b0 ;
b0 :
b0 9
08
b0 7
b0 6
bx 5
bx 4
bx 3
b10000000000000000000000000000100 2
b10000000000000000000000000000101 1
b10000000000000000000000000000011 0
b0 /
b0 .
0-
0,
1+
0*
b0 )
b0 (
b0 '
b0 &
b0 %
b0 $
b0 #
b0 "
0!
$end
#5000
1*
#10000
0*
#15000
1*
#20000
0*
0+
#25000
1*
#30000
0*
b1 4
b1 5
b0 3
1-
#35000
b1 T
1*
#40000
0*
b10111 /
b10111 7
b10111 O
b1 3
#45000
b10 T
1*
#50000
0*
b0 /
b0 7
b0 O
b10 3
#55000
b11 T
1*
#60000
0*
b10111 /
b10111 7
b10111 O
b11 3
#65000
b100 T
1*
#70000
0*
b0 /
b0 7
b0 O
b100 3
#75000
b101 T
1Y
b0 R
b0 S
b0 P
b0 Q
1*
#80000
0*
b11101001 /
b11101001 7
b11101001 O
b101 3
#85000
1A
b0 E
b0 U
b0 Z
b0 D
b0 V
b0 [
b0 C
b0 W
b0 \
b0 B
b0 X
b0 ]
b110 T
b11101001 S
b10111 Q
1Y
1*
#90000
0*
b0 /
b0 7
b0 O
b110 3
#95000
b101110 D
b101110 V
b101110 [
b111 T
b0 S
b0 Q
1Y
1A
b1 ^
1*
#100000
0*
b11101001 /
b11101001 7
b11101001 O
b111 3
#105000
b10 ^
b0 D
b0 V
b0 [
b0 T
b11101001 S
b10111 Q
1Y
1A
1*
#110000
0*
b0 /
b0 7
b0 O
0-
b1000 3
#115000
b101110 D
b101110 V
b101110 [
0Y
1A
b11 ^
18
1*
#120000
0*
#125000
b0 w
b1111110111110 x
b1111110111110 z
b0 y
b10100101 '"
b10100101 )"
b10100101 &"
b1011011 ("
b0 s
b1111111111110111110 t
b1111111111110111110 v
b0 u
1%"
1!
b0 ^
b101110 >
b101110 a
b101110 i
b101110 =
b101110 b
b101110 j
b11111010010 @
b11111010010 _
b11111010010 g
b101110 ?
b101110 `
b101110 h
18
0A
1*
#130000
0*
#135000
b101101 w
b1111111010010 x
b101101 y
b1111111010010 z
b101101 s
b1111111111111010010 t
b101101 u
b1111111111111010010 v
b10000001 '"
b0 )"
b0 &"
b1111111 ("
08
0%"
b1000010 #
b1000010 G
b1000010 #"
b1111110111110 '
b1111110111110 K
b1111110111110 }
b1000010 %
b1000010 I
b1000010 !"
b1111110111110 )
b1111110111110 M
b1111110111110 {
1!
1,
1*
#140000
0*
#145000
0!
1*
#146000
0,
b1000 3
