Verilog Projects/fft8/fft8_stage1.v
`timescale 1ns/1ps

module fft8_stage1 (
    input clk,
    input rst,
    input signed [7:0] xr, xi,
    input valid_in,

    output reg signed [8:0] sum_r, sum_i,
    output reg signed [8:0] diff_r, diff_i,
    output reg valid_out
);

// ============================
// Memory (store first 4 samples)
// ============================
reg signed [7:0] mem_r [0:3];
reg signed [7:0] mem_i [0:3];

reg [2:0] count;

// pipeline regs
reg signed [7:0] a_r, a_i;
reg signed [7:0] b_r, b_i;
reg valid_d;

// ============================
// Main logic
// ============================
always @(posedge clk or posedge rst) begin
    if (rst) begin
        count <= 0;
        valid_out <= 0;
        valid_d <= 0;
    end else begin
        valid_out <= 0;
        valid_d <= 0;

        if (valid_in) begin
            if (count < 4) begin
                // store first 4
                mem_r[count] <= xr;
                mem_i[count] <= xi;
            end else begin
                // fetch pair
                a_r <= mem_r[count - 4];
                a_i <= mem_i[count - 4];

                b_r <= xr;
                b_i <= xi;

                valid_d <= 1;
            end

            count <= count + 3'd1;
        end

        // compute butterfly (same cycle output)
        if (valid_d) begin
            sum_r  <= a_r + b_r;
            sum_i  <= a_i + b_i;

            diff_r <= a_r - b_r;
            diff_i <= a_i - b_i;

            valid_out <= 1;
        end
    end
end

endmodule

Verilog Projects/fft8/tb_fft_stage1.v
`timescale 1ns/1ps

module tb_fft8_stage1;

reg clk;
reg rst;
reg signed [7:0] xr, xi;
reg valid_in;

// ============================
// DUT outputs (UPDATED)
// ============================
wire signed [8:0] sum_r, sum_i;
wire signed [8:0] diff_r, diff_i;
wire valid_out;

// ============================
// Instantiate DUT
// ============================
fft8_stage1 dut (
    .clk(clk),
    .rst(rst),
    .xr(xr),
    .xi(xi),
    .valid_in(valid_in),
    .sum_r(sum_r),
    .sum_i(sum_i),
    .diff_r(diff_r),
    .diff_i(diff_i),
    .valid_out(valid_out)
);

// ============================
// Clock
// ============================
always #5 clk = ~clk;

// ============================
// File handles
// ============================
integer fr_real, fr_imag;
integer status_r, status_i;

// ============================
// Output file
// ============================
integer fout;

// ============================
// VCD dump
// ============================
initial begin
    $dumpfile("stage1_wave.vcd");
    $dumpvars(0, tb_fft8_stage1);
end

// ============================
// Test sequence
// ============================
integer i;

initial begin
    clk = 0;
    rst = 1;
    valid_in = 0;
    xr = 0;
    xi = 0;

    fout = $fopen("stage1_output.mem", "w");

    // ============================
    // Open input files
    // ============================
    fr_real = $fopen("input_real.mem", "r");
    fr_imag = $fopen("input_imag.mem", "r");

    if (fr_real == 0 || fr_imag == 0) begin
        $display("ERROR: Cannot open input files");
        $finish;
    end

    // Reset
    #20;
    rst = 0;

    // Start input
    #10;
    valid_in = 1;

    // ============================
    // Feed 8 samples
    // ============================
    for (i = 0; i < 8; i = i + 1) begin
        status_r = $fscanf(fr_real, "%d\n", xr);
        status_i = $fscanf(fr_imag, "%d\n", xi);

        if (status_r != 1 || status_i != 1) begin
            $display("ERROR reading input at i=%0d", i);
        end

        #10;
    end

    // Stop input
    valid_in = 0;
    xr = 0;
    xi = 0;

    // Wait for pipeline to flush
    #100;

    $fclose(fr_real);
    $fclose(fr_imag);
    $fclose(fout);

    $finish;
end

// ============================
// Capture outputs
// ============================
integer out_count = 0;

always @(posedge clk) begin
    if (valid_out) begin
        $display("OUT %0d: SUM=(%d,%d) DIFF=(%d,%d)", 
                  out_count, sum_r, sum_i, diff_r, diff_i);

        // store in file
        $fwrite(fout, "%d %d %d %d\n", sum_r, sum_i, diff_r, diff_i);

        out_count = out_count + 1;
    end
end

endmodule

Verilog Projects/fft8/stage1_wave.vcd
$date
	Wed Apr 08 13:24:48 2026
$end
$version
	Icarus Verilog
$end
$timescale
	1ps
$end
$scope module tb_fft8_stage1 $end
$var wire 1 ! valid_out $end
$var wire 9 " sum_r [8:0] $end
$var wire 9 # sum_i [8:0] $end
$var wire 9 $ diff_r [8:0] $end
$var wire 9 % diff_i [8:0] $end
$var reg 1 & clk $end
$var reg 1 ' rst $end
$var reg 1 ( valid_in $end
$var reg 8 ) xi [7:0] $end
$var reg 8 * xr [7:0] $end
$var integer 32 + fout [31:0] $end
$var integer 32 , fr_imag [31:0] $end
$var integer 32 - fr_real [31:0] $end
$var integer 32 . i [31:0] $end
$var integer 32 / out_count [31:0] $end
$var integer 32 0 status_i [31:0] $end
$var integer 32 1 status_r [31:0] $end
$scope module dut $end
$var wire 1 & clk $end
$var wire 1 ' rst $end
$var wire 1 ( valid_in $end
$var wire 8 2 xi [7:0] $end
$var wire 8 3 xr [7:0] $end
$var reg 8 4 a_i [7:0] $end
$var reg 8 5 a_r [7:0] $end
$var reg 8 6 b_i [7:0] $end
$var reg 8 7 b_r [7:0] $end
$var reg 3 8 count [2:0] $end
$var reg 9 9 diff_i [8:0] $end
$var reg 9 : diff_r [8:0] $end
$var reg 9 ; sum_i [8:0] $end
$var reg 9 < sum_r [8:0] $end
$var reg 1 = valid_d $end
$var reg 1 ! valid_out $end
$upscope $end
$upscope $end
$enddefinitions $end
$comment Show the parameter values. $end
$dumpall
$end
#0
$dumpvars
0=
bx <
bx ;
bx :
bx 9
b0 8
bx 7
bx 6
bx 5
bx 4
b0 3
b0 2
bx 1
bx 0
b0 /
bx .
b10000000000000000000000000000100 -
b10000000000000000000000000000101 ,
b10000000000000000000000000000011 +
b0 *
b0 )
0(
1'
0&
bx %
bx $
bx #
bx "
0!
$end
#5000
1&
#10000
0&
#15000
1&
#20000
0&
0'
#25000
1&
#30000
0&
b1 0
b1 1
b0 .
1(
#35000
b1 8
1&
#40000
0&
b10111 *
b10111 3
b1 .
#45000
b10 8
1&
#50000
0&
b0 *
b0 3
b10 .
#55000
b11 8
1&
#60000
0&
b10111 *
b10111 3
b11 .
#65000
b100 8
1&
#70000
0&
b0 *
b0 3
b100 .
#75000
b101 8
1=
b0 6
b0 7
b0 4
b0 5
1&
#80000
0&
b11101001 *
b11101001 3
b101 .
#85000
1!
b0 %
b0 9
b0 $
b0 :
b0 #
b0 ;
b0 "
b0 <
b110 8
b11101001 7
b10111 5
1=
1&
#90000
0&
b0 *
b0 3
b110 .
#95000
b101110 $
b101110 :
b111 8
b0 7
b0 5
1=
1!
b1 /
1&
#100000
0&
b11101001 *
b11101001 3
b111 .
#105000
b0 $
b0 :
b0 8
b11101001 7
b10111 5
1=
1!
b10 /
1&
#110000
0&
b0 *
b0 3
0(
b1000 .
#115000
b101110 $
b101110 :
0=
1!
b11 /
1&
#120000
0&
#125000
0!
b100 /
1&
