Verilog Projects/fft8/fft8_stage2.v
`timescale 1ns/1ps
module fft8_stage2(
    input clk,
    input rst,

    input signed [8:0] sum_in_r, sum_in_i,    // y0..y3
    input signed [8:0] diff_in_r, diff_in_i,  // y4..y7
    input valid_in,

    output reg signed [10:0] sum1_r, sum1_i,
    output reg signed [10:0] sum2_r, sum2_i,
    output reg signed [10:0] diff1_r, diff1_i,
    output reg signed [10:0] diff2_r, diff2_i,
    output reg valid_out
);

    // ============================
    // Memory to store first two inputs
    // ============================
    reg signed [8:0] sum_mem_r[0:1];   // y0, y1
    reg signed [8:0] sum_mem_i[0:1];
    reg signed [8:0] diff_mem_r[0:1];  // y4, y5
    reg signed [8:0] diff_mem_i[0:1];

    reg [1:0] count;  // counts 0..3

    always @(posedge clk or posedge rst) begin
        if(rst) begin
            count <= 0;
            valid_out <= 0;
            {sum1_r,sum1_i,sum2_r,sum2_i,
             diff1_r,diff1_i,diff2_r,diff2_i} <= 0;
        end else begin
            valid_out <= 0;

            if(valid_in) begin
                case(count)
                    2'd0: begin
                        // store y0 and y4
                        sum_mem_r[0]  <= sum_in_r;
                        sum_mem_i[0]  <= sum_in_i;
                        diff_mem_r[0] <= diff_in_r;
                        diff_mem_i[0] <= diff_in_i;
                    end
                    2'd1: begin
                        // store y1 and y5
                        sum_mem_r[1]  <= sum_in_r;
                        sum_mem_i[1]  <= sum_in_i;
                        diff_mem_r[1] <= diff_in_r;
                        diff_mem_i[1] <= diff_in_i;
                    end
                    2'd2: begin
                        // compute first pair outputs (z0, z2, z4, z6)
                        sum1_r  <= sum_mem_r[0] + sum_in_r; // z0 = y0 + y2
                        sum1_i  <= sum_mem_i[0] + sum_in_i;

                        sum2_r  <= sum_mem_r[0] - sum_in_r; // z2 = y0 - y2
                        sum2_i  <= sum_mem_i[0] - sum_in_i;

                        diff1_r <= diff_mem_r[0] + diff_in_i;  // z4 = y4 + (-j)*y6
                        diff1_i <= diff_mem_i[0] - diff_in_r;

                        diff2_r <= diff_mem_r[0] - diff_in_i;  // z6 = y4 - (-j)*y6
                        diff2_i <= diff_mem_i[0] + diff_in_r;

                        valid_out <= 1;
                    end
                    2'd3: begin
                        // compute second pair outputs (z1, z3, z5, z7)
                        sum1_r  <= sum_mem_r[1] + sum_in_r; // z1 = y1 + y3
                        sum1_i  <= sum_mem_i[1] + sum_in_i;

                        sum2_r  <= sum_mem_r[1] - sum_in_r; // z3 = y1 - y3
                        sum2_i  <= sum_mem_i[1] - sum_in_i;

                        diff1_r <= diff_mem_r[1] + diff_in_i; // z5 = y5 + (-j)*y7
                        diff1_i <= diff_mem_i[1] - diff_in_r;

                        diff2_r <= diff_mem_r[1] - diff_in_i; // z7 = y5 - (-j)*y7
                        diff2_i <= diff_mem_i[1] + diff_in_r;

                        valid_out <= 1;
                    end
                endcase

                count <= count + 2'd1;
            end
        end
    end

endmodule

Verilog Projects/fft8/fft8_stage1.v
`timescale 1ns/1ps

module fft8_stage1 (
    input clk,
    input rst,
    input signed [7:0] xr, xi,
    input valid_in,

    output reg signed [8:0] sum_r, sum_i,
    output reg signed [8:0] diff_r, diff_i,
    output reg valid_out
);

// ============================
// Memory (store first 4 samples)
// ============================
reg signed [7:0] mem_r [0:3];
reg signed [7:0] mem_i [0:3];

reg [2:0] count;

// pipeline regs
reg signed [7:0] a_r, a_i;
reg signed [7:0] b_r, b_i;
reg valid_d;

// ============================
// Main logic
// ============================
always @(posedge clk or posedge rst) begin
    if (rst) begin
        count <= 0;
        valid_out <= 0;
        valid_d <= 0;
    end else begin
        valid_out <= 0;
        valid_d <= 0;

        if (valid_in) begin
            if (count < 4) begin
                // store first 4
                mem_r[count] <= xr;
                mem_i[count] <= xi;
            end else begin
                // fetch pair
                a_r <= mem_r[count - 4];
                a_i <= mem_i[count - 4];

                b_r <= xr;
                b_i <= xi;

                valid_d <= 1;
            end

            count <= count + 3'd1;
        end

        // compute butterfly (same cycle output)
        if (valid_d) begin
            sum_r  <= a_r + b_r;
            sum_i  <= a_i + b_i;

            diff_r <= a_r - b_r;
            diff_i <= a_i - b_i;

            valid_out <= 1;
        end
    end
end

endmodule

Verilog Projects/fft8/tb_fft8_stage12.v
`timescale 1ns/1ps

module tb_fft8_stage12_pairwise;

reg clk;
reg rst;
reg signed [7:0] xr, xi;
reg valid_in;

// ============================
// Stage-1 outputs
// ============================
wire signed [8:0] s1_sum_r, s1_sum_i;
wire signed [8:0] s1_diff_r, s1_diff_i;
wire s1_valid;

// ============================
// Stage-2 outputs (PAIRWISE)
// ============================
wire signed [10:0] s2_sum1_r, s2_sum1_i;
wire signed [10:0] s2_sum2_r, s2_sum2_i;
wire signed [10:0] s2_diff1_r, s2_diff1_i;
wire signed [10:0] s2_diff2_r, s2_diff2_i;
wire s2_valid_out;

// ============================
// Instantiate Stage-1
// ============================
fft8_stage1 stage1 (
    .clk(clk),
    .rst(rst),
    .xr(xr),
    .xi(xi),
    .valid_in(valid_in),
    .sum_r(s1_sum_r),
    .sum_i(s1_sum_i),
    .diff_r(s1_diff_r),
    .diff_i(s1_diff_i),
    .valid_out(s1_valid)
);

// ============================
// Instantiate Stage-2 (PAIRWISE VERSION)
// ============================
fft8_stage2 stage2 (
    .clk(clk),
    .rst(rst),
    .sum_in_r(s1_sum_r),
    .sum_in_i(s1_sum_i),
    .diff_in_r(s1_diff_r),
    .diff_in_i(s1_diff_i),
    .valid_in(s1_valid),
    .sum1_r(s2_sum1_r),
    .sum1_i(s2_sum1_i),
    .sum2_r(s2_sum2_r),
    .sum2_i(s2_sum2_i),
    .diff1_r(s2_diff1_r),
    .diff1_i(s2_diff1_i),
    .diff2_r(s2_diff2_r),
    .diff2_i(s2_diff2_i),
    .valid_out(s2_valid_out)
);

// ============================
// Clock
// ============================
always #5 clk = ~clk;

// ============================
// File I/O
// ============================
integer fr_real, fr_imag;
integer fout;
integer status_r, status_i;
integer i;

// ============================
// VCD
// ============================
initial begin
    $dumpfile("stage12_wave.vcd");
    $dumpvars(0, tb_fft8_stage12_pairwise);
end

// ============================
// Stimulus
// ============================
initial begin
    clk = 0;
    rst = 1;
    valid_in = 0;
    xr = 0;
    xi = 0;

    fout = $fopen("stage12_output.mem", "w");

    fr_real = $fopen("input_real.mem", "r");
    fr_imag = $fopen("input_imag.mem", "r");

    if (fr_real == 0 || fr_imag == 0) begin
        $display("ERROR opening input files");
        $finish;
    end

    #20;
    rst = 0;
    #10;
    valid_in = 1;

    // feed 8 samples
    for (i = 0; i < 8; i = i + 1) begin
        status_r = $fscanf(fr_real, "%d\n", xr);
        status_i = $fscanf(fr_imag, "%d\n", xi);

        if (status_r != 1 || status_i != 1)
            $display("ERROR reading input at %0d", i);

        #10;
    end

    valid_in = 0;
    xr = 0;
    xi = 0;

    #200;

    $fclose(fr_real);
    $fclose(fr_imag);
    $fclose(fout);

    $finish;
end

// ============================
// Capture Stage-2 outputs
// ============================
integer out_count = 0;

always @(posedge clk) begin
    if (s2_valid_out) begin
        $display("OUT %0d: SUM1=(%d,%d) SUM2=(%d,%d) DIFF1=(%d,%d) DIFF2=(%d,%d)",
                  out_count,
                  s2_sum1_r, s2_sum1_i,
                  s2_sum2_r, s2_sum2_i,
                  s2_diff1_r, s2_diff1_i,
                  s2_diff2_r, s2_diff2_i);

        $fwrite(fout, "%d %d %d %d %d %d %d %d\n",
                  s2_sum1_r, s2_sum1_i,
                  s2_sum2_r, s2_sum2_i,
                  s2_diff1_r, s2_diff1_i,
                  s2_diff2_r, s2_diff2_i);

        out_count = out_count + 1;
    end
end

endmodule

Verilog Projects/fft8/stage12_wave.vcd
$date
	Wed Apr 08 13:25:00 2026
$end
$version
	Icarus Verilog
$end
$timescale
	1ps
$end
$scope module tb_fft8_stage12_pairwise $end
$var wire 1 ! s2_valid_out $end
$var wire 11 " s2_sum2_r [10:0] $end
$var wire 11 # s2_sum2_i [10:0] $end
$var wire 11 $ s2_sum1_r [10:0] $end
$var wire 11 % s2_sum1_i [10:0] $end
$var wire 11 & s2_diff2_r [10:0] $end
$var wire 11 ' s2_diff2_i [10:0] $end
$var wire 11 ( s2_diff1_r [10:0] $end
$var wire 11 ) s2_diff1_i [10:0] $end
$var wire 1 * s1_valid $end
$var wire 9 + s1_sum_r [8:0] $end
$var wire 9 , s1_sum_i [8:0] $end
$var wire 9 - s1_diff_r [8:0] $end
$var wire 9 . s1_diff_i [8:0] $end
$var reg 1 / clk $end
$var reg 1 0 rst $end
$var reg 1 1 valid_in $end
$var reg 8 2 xi [7:0] $end
$var reg 8 3 xr [7:0] $end
$var integer 32 4 fout [31:0] $end
$var integer 32 5 fr_imag [31:0] $end
$var integer 32 6 fr_real [31:0] $end
$var integer 32 7 i [31:0] $end
$var integer 32 8 out_count [31:0] $end
$var integer 32 9 status_i [31:0] $end
$var integer 32 : status_r [31:0] $end
$scope module stage1 $end
$var wire 1 / clk $end
$var wire 1 0 rst $end
$var wire 1 1 valid_in $end
$var wire 8 ; xi [7:0] $end
$var wire 8 < xr [7:0] $end
$var reg 8 = a_i [7:0] $end
$var reg 8 > a_r [7:0] $end
$var reg 8 ? b_i [7:0] $end
$var reg 8 @ b_r [7:0] $end
$var reg 3 A count [2:0] $end
$var reg 9 B diff_i [8:0] $end
$var reg 9 C diff_r [8:0] $end
$var reg 9 D sum_i [8:0] $end
$var reg 9 E sum_r [8:0] $end
$var reg 1 F valid_d $end
$var reg 1 * valid_out $end
$upscope $end
$scope module stage2 $end
$var wire 1 / clk $end
$var wire 9 G diff_in_i [8:0] $end
$var wire 9 H diff_in_r [8:0] $end
$var wire 1 0 rst $end
$var wire 9 I sum_in_i [8:0] $end
$var wire 9 J sum_in_r [8:0] $end
$var wire 1 * valid_in $end
$var reg 2 K count [1:0] $end
$var reg 11 L diff1_i [10:0] $end
$var reg 11 M diff1_r [10:0] $end
$var reg 11 N diff2_i [10:0] $end
$var reg 11 O diff2_r [10:0] $end
$var reg 11 P sum1_i [10:0] $end
$var reg 11 Q sum1_r [10:0] $end
$var reg 11 R sum2_i [10:0] $end
$var reg 11 S sum2_r [10:0] $end
$var reg 1 ! valid_out $end
$upscope $end
$upscope $end
$enddefinitions $end
$comment Show the parameter values. $end
$dumpall
$end
#0
$dumpvars
b0 S
b0 R
b0 Q
b0 P
b0 O
b0 N
b0 M
b0 L
b0 K
bx J
bx I
bx H
bx G
0F
bx E
bx D
bx C
bx B
b0 A
bx @
bx ?
bx >
bx =
b0 <
b0 ;
bx :
bx 9
b0 8
bx 7
b10000000000000000000000000000100 6
b10000000000000000000000000000101 5
b10000000000000000000000000000011 4
b0 3
b0 2
01
10
0/
bx .
bx -
bx ,
bx +
0*
b0 )
b0 (
b0 '
b0 &
b0 %
b0 $
b0 #
b0 "
0!
$end
#5000
1/
#10000
0/
#15000
1/
#20000
0/
00
#25000
1/
#30000
0/
b1 9
b1 :
b0 7
11
#35000
b1 A
1/
#40000
0/
b10111 3
b10111 <
b1 7
#45000
b10 A
1/
#50000
0/
b0 3
b0 <
b10 7
#55000
b11 A
1/
#60000
0/
b10111 3
b10111 <
b11 7
#65000
b100 A
1/
#70000
0/
b0 3
b0 <
b100 7
#75000
b101 A
1F
b0 ?
b0 @
b0 =
b0 >
1/
#80000
0/
b11101001 3
b11101001 <
b101 7
#85000
1*
b0 .
b0 B
b0 G
b0 -
b0 C
b0 H
b0 ,
b0 D
b0 I
b0 +
b0 E
b0 J
b110 A
b11101001 @
b10111 >
1F
1/
#90000
0/
b0 3
b0 <
b110 7
#95000
b101110 -
b101110 C
b101110 H
b111 A
b0 @
b0 >
1F
1*
b1 K
1/
#100000
0/
b11101001 3
b11101001 <
b111 7
#105000
b10 K
b0 -
b0 C
b0 H
b0 A
b11101001 @
b10111 >
1F
1*
1/
#110000
0/
b0 3
b0 <
01
b1000 7
#115000
b101110 -
b101110 C
b101110 H
0F
1*
b11 K
1!
1/
#120000
0/
#125000
b0 K
b101110 '
b101110 N
b101110 &
b101110 O
b11111010010 )
b11111010010 L
b101110 (
b101110 M
1!
0*
b1 8
1/
#130000
0/
#135000
0!
b10 8
1/
