Verilog Projects/Binary_to_BCD/double_dabble.v
module bin_to_bcd #(
    parameter bin_width = 8,
    parameter bcd_digits = (bin_width*3)/10 +1
) (
    input [bin_width-1:0]bin,
    output reg [(4*bcd_digits-1):0]bcd
);
  localparam n = bin_width + 4 * bcd_digits;
  reg [(n-1) : 0]dig;
  always@(*) begin
    dig = {n{1'b0}};
    dig[bin_width-1:0] = bin;  
    for(integer i =0 ; i<bin_width ; i = i+1) begin
        for(integer j=0 ;j<bcd_digits;j=j+1) begin
            if(dig[bin_width+4*j+:4] >=5) dig[bin_width+4*j+:4] = dig[bin_width+4*j +: 4] +3;
        end
        dig = dig << 1;
    end
    bcd = dig [n-1:bin_width];
  end  
endmodule

Verilog Projects/Binary_to_BCD/tb_double_dabble.v
`timescale 1ns / 1ps

module tb_bin_to_bcd;

    // Parameters
    parameter BIN_WIDTH = 8;
    parameter BCD_DIGITS = (BIN_WIDTH*3)/10 + 1;

    // DUT I/O
    reg  [BIN_WIDTH-1:0] bin;
    wire [(4*BCD_DIGITS-1):0] bcd;

    // Instantiate the DUT (Design Under Test)
    bin_to_bcd #(
        .bin_width(BIN_WIDTH),
        .bcd_digits(BCD_DIGITS)
    ) uut (
        .bin(bin),
        .bcd(bcd)
    );

    // Task to print BCD as decimal digits
    task display_bcd;
        integer i;
        begin
            $write("BCD Digits: ");
            for (i = BCD_DIGITS-1; i >= 0; i = i - 1)
                $write("%0d", bcd[4*i +: 4]);
            $write("\n");
        end
    endtask

    // VCD dump initialization
    initial begin
        $dumpfile("bin_to_bcd_tb.vcd");   // Name of the dump file
        $dumpvars(0, tb_bin_to_bcd);      // Dump all variables in this module
    end

    // Stimulus
    initial begin
        $display("Testing Binary to BCD Conversion");
        $display("-------------------------------");

        bin = 8'd0;   #10; $write("Binary: %0d -> ", bin); display_bcd();
        bin = 8'd5;   #10; $write("Binary: %0d -> ", bin); display_bcd();
        bin = 8'd9;   #10; $write("Binary: %0d -> ", bin); display_bcd();
        bin = 8'd12;  #10; $write("Binary: %0d -> ", bin); display_bcd();
        bin = 8'd45;  #10; $write("Binary: %0d -> ", bin); display_bcd();
        bin = 8'd99;  #10; $write("Binary: %0d -> ", bin); display_bcd();
        bin = 8'd123; #10; $write("Binary: %0d -> ", bin); display_bcd();
        bin = 8'd255; #10; $write("Binary: %0d -> ", bin); display_bcd();

        $finish;
    end

endmodule

Verilog Projects/Binary_to_BCD/bin_to_bcd_tb.vcd
$date
	Tue May 20 11:50:26 2025
$end
$version
	Icarus Verilog
$end
$timescale
	1ps
$end
$scope module tb_bin_to_bcd $end
$var wire 12 ! bcd [11:0] $end
$var parameter 65 " BCD_DIGITS $end
$var parameter 32 # BIN_WIDTH $end
$var reg 8 $ bin [7:0] $end
$scope module uut $end
$var wire 8 % bin [7:0] $end
$var parameter 65 & bcd_digits $end
$var parameter 32 ' bin_width $end
$var parameter 98 ( n $end
$var reg 12 ) bcd [11:0] $end
$var reg 20 * dig [19:0] $end
$scope begin $ivl_for_loop0 $end
$var integer 32 + i [31:0] $end
$scope begin $ivl_for_loop1 $end
$var integer 32 , j [31:0] $end
$upscope $end
$upscope $end
$upscope $end
$scope task display_bcd $end
$var integer 32 - i [31:0] $end
$upscope $end
$upscope $end
$enddefinitions $end
$comment Show the parameter values. $end
$dumpall
b10100 (
b1000 '
b11 &
b1000 #
b11 "
$end
#0
$dumpvars
bx -
b11 ,
b1000 +
b0 *
b0 )
b0 %
b0 $
b0 !
$end
#10000
b101 !
b101 )
b11 ,
b1000 +
b10100000000 *
b101 $
b101 %
b11111111111111111111111111111111 -
#20000
b1001 !
b1001 )
b11 ,
b1000 +
b100100000000 *
b1001 $
b1001 %
b11111111111111111111111111111111 -
#30000
b10010 !
b10010 )
b11 ,
b1000 +
b1001000000000 *
b1100 $
b1100 %
b11111111111111111111111111111111 -
#40000
b1000101 !
b1000101 )
b11 ,
b1000 +
b100010100000000 *
b101101 $
b101101 %
b11111111111111111111111111111111 -
#50000
b10011001 !
b10011001 )
b11 ,
b1000 +
b1001100100000000 *
b1100011 $
b1100011 %
b11111111111111111111111111111111 -
#60000
b100100011 !
b100100011 )
b11 ,
b1000 +
b10010001100000000 *
b1111011 $
b1111011 %
b11111111111111111111111111111111 -
#70000
b1001010101 !
b1001010101 )
b11 ,
b1000 +
b100101010100000000 *
b11111111 $
b11111111 %
b11111111111111111111111111111111 -
#80000
b11111111111111111111111111111111 -
