Verilog Projects/4-bit_ALU/shift_right.v
module shift_right (
    input [3:0]A,
    input [1:0]B,
    output [3:0]y
);
    assign y = A >> B;
endmodule

Verilog Projects/4-bit_ALU/shift_left.v
module shift_left (
    input [3:0]A,
    input [1:0]B,
    output [3:0]y
);
    assign y = A<<B;
endmodule

Verilog Projects/4-bit_ALU/not.v
module not_g (
    input [3:0]A,
    output [3:0]y
);
    assign y = ~A;
endmodule

Verilog Projects/4-bit_ALU/xor.v
module xor_g (
    input [3:0] A,
    input [3:0] B,
    output [3:0] y
);
assign y = A ^ B;    
endmodule

Verilog Projects/4-bit_ALU/or.v
module or_g (
    input [3:0] A,
    input [3:0] B,
    output [3:0] y
);
assign y = A | B;
    
endmodule

Verilog Projects/4-bit_ALU/and.v
module and_g (
    input [3:0] A,
    input [3:0] B,
    output [3:0] y
);
    assign y = A & B;
endmodule

Verilog Projects/4-bit_ALU/sub.v
module sub (
    input [3:0]A,
    input [3:0]B,
    output [3:0]Diff,
    output b_out
);
    wire [4:0]result;
    assign result = {1'b0,A} - {1'b0,B};
    assign Diff = result[3:0];
    assign b_out = result[4];
endmodule

Verilog Projects/4-bit_ALU/add.v
module add (
    input [3:0]A,
    input [3:0]B,
    output [3:0]sum,
    output c_out
);
wire [4:0] result;
assign result = A+B;
assign sum = result[3:0];
assign c_out = result[4]; 
    
endmodule

Verilog Projects/4-bit_ALU/alu_top.v
module alu (
    input [3:0]A,
    input [3:0]B,
    input [2:0]sel,
    output reg [3:0]y,
    output reg c_out
);
wire carry_out,borrow_out;
wire [3:0] and_out,or_out,xor_out,not_out,shift_right_out,shift_left_out,sum_out,diff_out;
wire [1:0] shift_by;
assign shift_by = B[1:0];
add add_inst (.A(A),.B(B),.sum(sum_out),.c_out(carry_out));
sub sub_inst (.A(A),.B(B),.Diff(diff_out),.b_out(borrow_out));
and_g and_inst (.A(A),.B(B),.y(and_out));
or_g or_inst (.A(A),.B(B),.y(or_out));
xor_g xor_inst (.A(A),.B(B),.y(xor_out));
not_g not_inst (.A(A),.y(not_out));
shift_left shift_left_inst (.A(A),.B(shift_by),.y(shift_left_out));
shift_right shift_right_inst (.A(A),.B(shift_by),.y(shift_right_out));
always @(*) begin
    case (sel)
        3'b000: begin   // Addition
            y = sum_out;
            c_out = carry_out;
        end
        3'b001: begin   // Subtraction
            y = diff_out;
            c_out = borrow_out;
        end
        3'b010: begin   // AND
            y = and_out;
            c_out = 1'b0;
        end
        3'b011: begin   // OR
            y = or_out;
            c_out = 1'b0;
        end
        3'b100: begin   // XOR
            y = xor_out;
            c_out = 1'b0;
        end
        3'b101: begin   // NOT (on A only)
            y = not_out;
            c_out = 1'b0;
        end
        3'b110: begin   // Shift Left
            y = shift_left_out;
            c_out = 1'b0;
        end
        3'b111: begin   // Shift Right
            y = shift_right_out;
            c_out = 1'b0;
        end
        default: begin
            y = 4'b0000;
            c_out = 1'b0;
        end
    endcase
end

endmodule

Verilog Projects/4-bit_ALU/tb_alu.v
`timescale 1ns / 1ps

module alu_tb;

    // Inputs
    reg [3:0] A;
    reg [3:0] B;
    reg [2:0] sel;

    // Outputs
    wire [3:0] y;
    wire c_out;

    // Instantiate the ALU
    alu uut (
        .A(A),
        .B(B),
        .sel(sel),
        .y(y),
        .c_out(c_out)
    );

    initial begin
        // Set up VCD file for GTKWave
        $dumpfile("alu_tb.vcd");   // Name of the output VCD file
        $dumpvars(0, alu_tb);      // Dump all signals in this module

        // Monitor changes
        $monitor("Time=%0t A=%b B=%b sel=%b => y=%b c_out=%b", $time, A, B, sel, y, c_out);

        // Test ADD (sel = 000)
        A = 4'b0011; B = 4'b0101; sel = 3'b000; #10;

        // Test SUB (sel = 001)
        A = 4'b0110; B = 4'b0011; sel = 3'b001; #10;

        // Test AND (sel = 010)
        A = 4'b1100; B = 4'b1010; sel = 3'b010; #10;

        // Test OR (sel = 011)
        A = 4'b1100; B = 4'b1010; sel = 3'b011; #10;

        // Test XOR (sel = 100)
        A = 4'b1100; B = 4'b1010; sel = 3'b100; #10;

        // Test NOT (sel = 101)
        A = 4'b1100; B = 4'b0000; sel = 3'b101; #10;

        // Test SHIFT LEFT (sel = 110)
        A = 4'b0001; B = 4'b0010; sel = 3'b110; #10;

        // Test SHIFT RIGHT (sel = 111)
        A = 4'b1000; B = 4'b0001; sel = 3'b111; #10;

        // End simulation
        $finish;
    end

endmodule

Verilog Projects/4-bit_ALU/alu_tb.vcd
$date
	Mon May 19 12:06:51 2025
$end
$version
	Icarus Verilog
$end
$timescale
	1ps
$end
$scope module alu_tb $end
$var wire 4 ! y [3:0] $end
$var wire 1 " c_out $end
$var reg 4 # A [3:0] $end
$var reg 4 $ B [3:0] $end
$var reg 3 % sel [2:0] $end
$scope module uut $end
$var wire 4 & A [3:0] $end
$var wire 4 ' B [3:0] $end
$var wire 3 ( sel [2:0] $end
$var wire 4 ) xor_out [3:0] $end
$var wire 4 * sum_out [3:0] $end
$var wire 4 + shift_right_out [3:0] $end
$var wire 4 , shift_left_out [3:0] $end
$var wire 2 - shift_by [1:0] $end
$var wire 4 . or_out [3:0] $end
$var wire 4 / not_out [3:0] $end
$var wire 4 0 diff_out [3:0] $end
$var wire 1 1 carry_out $end
$var wire 1 2 borrow_out $end
$var wire 4 3 and_out [3:0] $end
$var reg 1 " c_out $end
$var reg 4 4 y [3:0] $end
$scope module add_inst $end
$var wire 4 5 A [3:0] $end
$var wire 4 6 B [3:0] $end
$var wire 4 7 sum [3:0] $end
$var wire 5 8 result [4:0] $end
$var wire 1 1 c_out $end
$upscope $end
$scope module and_inst $end
$var wire 4 9 A [3:0] $end
$var wire 4 : B [3:0] $end
$var wire 4 ; y [3:0] $end
$upscope $end
$scope module not_inst $end
$var wire 4 < A [3:0] $end
$var wire 4 = y [3:0] $end
$upscope $end
$scope module or_inst $end
$var wire 4 > A [3:0] $end
$var wire 4 ? B [3:0] $end
$var wire 4 @ y [3:0] $end
$upscope $end
$scope module shift_left_inst $end
$var wire 4 A A [3:0] $end
$var wire 2 B B [1:0] $end
$var wire 4 C y [3:0] $end
$upscope $end
$scope module shift_right_inst $end
$var wire 4 D A [3:0] $end
$var wire 2 E B [1:0] $end
$var wire 4 F y [3:0] $end
$upscope $end
$scope module sub_inst $end
$var wire 4 G A [3:0] $end
$var wire 4 H B [3:0] $end
$var wire 5 I result [4:0] $end
$var wire 1 2 b_out $end
$var wire 4 J Diff [3:0] $end
$upscope $end
$scope module xor_inst $end
$var wire 4 K A [3:0] $end
$var wire 4 L B [3:0] $end
$var wire 4 M y [3:0] $end
$upscope $end
$upscope $end
$upscope $end
$enddefinitions $end
$comment Show the parameter values. $end
$dumpall
$end
#0
$dumpvars
b110 M
b101 L
b11 K
b1110 J
b11110 I
b101 H
b11 G
b1 F
b1 E
b11 D
b110 C
b1 B
b11 A
b111 @
b101 ?
b11 >
b1100 =
b11 <
b1 ;
b101 :
b11 9
b1000 8
b1000 7
b101 6
b11 5
b1000 4
b1 3
12
01
b1110 0
b1100 /
b111 .
b1 -
b110 ,
b1 +
b1000 *
b110 )
b0 (
b101 '
b11 &
b0 %
b101 $
b11 #
0"
b1000 !
$end
#10000
b11 -
b11 B
b11 E
b1001 *
b1001 7
b10 3
b10 ;
b1001 /
b1001 =
b11 !
b11 4
b11 0
b11 J
02
b101 )
b101 M
b1 %
b1 (
b11 $
b11 '
b11 6
b11 :
b11 ?
b11 H
b11 L
b1001 8
b0 ,
b0 C
b0 +
b0 F
b11 I
b110 #
b110 &
b110 5
b110 9
b110 <
b110 >
b110 A
b110 D
b110 G
b110 K
#20000
b10 -
b10 B
b10 E
11
b110 *
b110 7
b1000 3
b1000 ;
b11 /
b11 =
b1110 .
b1110 @
b1000 !
b1000 4
b10 0
b10 J
b110 )
b110 M
b10 %
b10 (
b1010 $
b1010 '
b1010 6
b1010 :
b1010 ?
b1010 H
b1010 L
b10110 8
b11 +
b11 F
b10 I
b1100 #
b1100 &
b1100 5
b1100 9
b1100 <
b1100 >
b1100 A
b1100 D
b1100 G
b1100 K
#30000
b1110 !
b1110 4
b11 %
b11 (
#40000
b110 !
b110 4
b100 %
b100 (
#50000
b11 !
b11 4
b1100 ,
b1100 C
b1100 +
b1100 F
b0 -
b0 B
b0 E
b1100 *
b1100 7
01
b0 3
b0 ;
b1100 .
b1100 @
b1100 0
b1100 J
b1100 )
b1100 M
b101 %
b101 (
b1100 8
b1100 I
b0 $
b0 '
b0 6
b0 :
b0 ?
b0 H
b0 L
#60000
b10 -
b10 B
b10 E
12
b11 *
b11 7
b1110 /
b1110 =
b11 .
b11 @
b100 !
b100 4
b1111 0
b1111 J
b11 )
b11 M
b110 %
b110 (
b10 $
b10 '
b10 6
b10 :
b10 ?
b10 H
b10 L
b11 8
b100 ,
b100 C
b0 +
b0 F
b11111 I
b1 #
b1 &
b1 5
b1 9
b1 <
b1 >
b1 A
b1 D
b1 G
b1 K
#70000
b1 -
b1 B
b1 E
b1001 *
b1001 7
b111 /
b111 =
b1001 .
b1001 @
b100 !
b100 4
b111 0
b111 J
02
b1001 )
b1001 M
b111 %
b111 (
b1 $
b1 '
b1 6
b1 :
b1 ?
b1 H
b1 L
b1001 8
b0 ,
b0 C
b100 +
b100 F
b111 I
b1000 #
b1000 &
b1000 5
b1000 9
b1000 <
b1000 >
b1000 A
b1000 D
b1000 G
b1000 K
